[
  {
    "Project_Title": "Brazil 2017 - Atlantic Forest Restoration",
    "Longitude": -5343364.0559,
    "Latitude": -2773709.9021
  },
  {
    "Project_Title": "Oregon 2018 - Spring",
    "Longitude": -13420031.9344,
    "Latitude": 5435180.8684
  },
  {
    "Project_Title": "India 2018 - Fruit tree planting",
    "Longitude": 8745917.3175,
    "Latitude": 2809803.9175
  },
  {
    "Project_Title": "Haiti 2018 - Smallholders Farmers Alliance",
    "Longitude": -8065837.6052,
    "Latitude": 2137004.8862
  },
  {
    "Project_Title": "California 2018 - Spring ",
    "Longitude": -13738232.2423,
    "Latitude": 4767274.8876
  },
  {
    "Project_Title": "Vermont 2018 - Fall",
    "Longitude": -8052460.676,
    "Latitude": 5428747.8998
  },
  {
    "Project_Title": "Kenya 2018 - Kijabe Forest",
    "Longitude": 4076009.353,
    "Latitude": -105927.5911
  },
  {
    "Project_Title": "British Columbia 2018 – Spring ",
    "Longitude": -13567192.9616,
    "Latitude": 6675103.6213
  },
  {
    "Project_Title": "Colorado 2018 - Fall",
    "Longitude": -11731955.5687,
    "Latitude": 4872876.6274
  },
  {
    "Project_Title": "Ecuador 2018 - Mindo Cloud Forest",
    "Longitude": -8826881.7643,
    "Latitude": 10333.9042
  },
  {
    "Project_Title": "Rwanda 2018 - Gishwati-Mukura Reforestation ",
    "Longitude": 3267338.8196,
    "Latitude": -202239.8358
  },
  {
    "Project_Title": "Tanzania 2018 - Friends of Usambara Society",
    "Longitude": 4262746.129,
    "Latitude": -534272.1014
  },
  {
    "Project_Title": "California 2018 - Sugar Pine Fall Planting ",
    "Longitude": -13366967.2689,
    "Latitude": 4714667.4817
  },
  {
    "Project_Title": "California 2018 - Mendocino Fire Restoration ",
    "Longitude": -13740164.7486,
    "Latitude": 4783453.8914
  },
  {
    "Project_Title": "Rwanda 2018- Global Giving campaign",
    "Longitude": -216372.3288,
    "Latitude": 3488208.451
  },
  {
    "Project_Title": "Tanzania 2018 - Tree Tracker",
    "Longitude": 4135448.0611,
    "Latitude": -354316.6697
  },
  {
    "Project_Title": "California 2018 - Oak Tree Distribution",
    "Longitude": -13293543.2705,
    "Latitude": 4408243.856
  },
  {
    "Project_Title": "Brazil 2018 - Atlantic Forest Restoration",
    "Longitude": -5343364.0559,
    "Latitude": -2773709.9021
  },
  {
    "Project_Title": "Indonesia 2018 - Tanjung Puting National Park, Central Borneo",
    "Longitude": 12458349.1875,
    "Latitude": -344857.0945
  },
  {
    "Project_Title": "Peru 2018 - Madre de Dios (Phase 1)",
    "Longitude": -7702587.19,
    "Latitude": -1411541.4531
  },
  {
    "Project_Title": "New York 2018 - Upper Susquehanna Coalition",
    "Longitude": -8588828.9294,
    "Latitude": 5215365.3012
  },
  {
    "Project_Title": "California 2018 - Re-Oak California",
    "Longitude": -13648708.2729,
    "Latitude": 4636622.9785
  },
  {
    "Project_Title": "Texas 2018 - Blanco River",
    "Longitude": -10911169.2446,
    "Latitude": 3495428.9138
  },
  {
    "Project_Title": "Washington 2018 - Jennings Memorial Park Planting",
    "Longitude": -13598814.3762,
    "Latitude": 6116624.3195
  },
  {
    "Project_Title": "Australia 2019 - Tassie Island Ark Project",
    "Longitude": 16398504.1337,
    "Latitude": -5137725.2935
  },
  {
    "Project_Title": "Ethiopia 2019 - Loka Abaya Woreda Restoration ",
    "Longitude": 3962346.5869,
    "Latitude": 681568.9834
  },
  {
    "Project_Title": "Guatemala 2019 - Nursery Project ",
    "Longitude": -10193147.1744,
    "Latitude": 1810001.9042
  },
  {
    "Project_Title": "Oregon 2018 - 2019 - Fall/Spring",
    "Longitude": -13555584.2311,
    "Latitude": 5729970.4408
  },
  {
    "Project_Title": "Quebec 2019 - Mont St. Hilaire",
    "Longitude": -8147658.9894,
    "Latitude": 5710470.3928
  },
  {
    "Project_Title": "Vermont 2019 - Connecticut River Riparian Restoration ",
    "Longitude": -8052460.676,
    "Latitude": 5428747.8998
  },
  {
    "Project_Title": "Brazil 2019 - Atlantic Forest Restoration",
    "Longitude": -5343364.0559,
    "Latitude": -2773709.9021
  },
  {
    "Project_Title": "Florida 2019 - Seminole Forest",
    "Longitude": -9085853.4284,
    "Latitude": 3372237.7049
  },
  {
    "Project_Title": "Kenya 2019 - Kijabe Forest",
    "Longitude": 4073136.2737,
    "Latitude": -104006.7848
  },
  {
    "Project_Title": "California 2019 - Redwood Valley Fire Restoration",
    "Longitude": -13718365.7874,
    "Latitude": 4770121.919
  },
  {
    "Project_Title": "California 2019 - Moonlight Fire Restoration",
    "Longitude": -13438346.384,
    "Latitude": 4897805.1176
  },
  {
    "Project_Title": "California 2019 - King Fire Restoration",
    "Longitude": -13400357.9955,
    "Latitude": 4715221.4583
  },
  {
    "Project_Title": "California 2019 - Little Valley Fire Restoration",
    "Longitude": -13351102.3491,
    "Latitude": 4763839.5336
  },
  {
    "Project_Title": "India 2019 - Fruit tree & mangrove planting",
    "Longitude": 9606815.2825,
    "Latitude": 3118436.3244
  },
  {
    "Project_Title": "Indonesia 2019 - Tanjung Puting National Park, Central Borneo ",
    "Longitude": 12458187.2844,
    "Latitude": -298511.1515
  },
  {
    "Project_Title": "British Columbia 2019 - Spring",
    "Longitude": -13696564.5977,
    "Latitude": 6785371.859
  },
  {
    "Project_Title": "Rwanda 2019 - Coffee Trees for Coffee Day",
    "Longitude": 3316883.5716,
    "Latitude": -200855.7799
  },
  {
    "Project_Title": "Colorado 2019 - Highway 149 Spruce Beetle Restoration",
    "Longitude": -11935641.9617,
    "Latitude": 4577626.7994
  },
  {
    "Project_Title": "Idaho 2019 - Pete Forks Wildfire Planting",
    "Longitude": -12841050.8025,
    "Latitude": 5809894.6668
  },
  {
    "Project_Title": "Montana 2019 - Flathead National Montana Forest: Acquired Lands Restoration",
    "Longitude": -12670749.2361,
    "Latitude": 6098710.5053
  },
  {
    "Project_Title": "Wyoming 2019 - Shoshone National Forest: Beem Salvage Planting",
    "Longitude": -12190370.4563,
    "Latitude": 5464049.5182
  },
  {
    "Project_Title": "New Mexico 2019 - Scott Able Fire Restoration/Lincoln National Forest",
    "Longitude": -11748390.8897,
    "Latitude": 3878825.4312
  },
  {
    "Project_Title": "California 2019 - Emerald Fire Restoration ",
    "Longitude": -13363761.9355,
    "Latitude": 4714995.4265
  },
  {
    "Project_Title": "California 2019 - Tahoe National Forest Restoration",
    "Longitude": -13421072.215,
    "Latitude": 4802553.1492
  },
  {
    "Project_Title": "Tennessee 2019 - Cherokee National Forest Planting",
    "Longitude": -9132931.2158,
    "Latitude": 4381413.3529
  },
  {
    "Project_Title": "South Africa 2019 - Buffelsdraai Community Reforestation Project",
    "Longitude": 3449908.907,
    "Latitude": -3456252.5883
  },
  {
    "Project_Title": "Ghana 2019 - Tongo Hills",
    "Longitude": -85685.3494,
    "Latitude": 1199153.2776
  },
  {
    "Project_Title": "Michigan 2019 - The Greening of Detroit",
    "Longitude": -9244617.8383,
    "Latitude": 5210755.0164
  },
  {
    "Project_Title": "Georgia 2019 - Keep Georgia Beautiful",
    "Longitude": -9288627.665,
    "Latitude": 3928251.6315
  },
  {
    "Project_Title": "New York 2019 - Butternut Creek and Morris Brook Restoration",
    "Longitude": -8380436.4437,
    "Latitude": 5237519.8287
  },
  {
    "Project_Title": "Ethiopia 2019 - Amhara Region",
    "Longitude": 4109628.1732,
    "Latitude": 1241311.2945
  },
  {
    "Project_Title": "Rwanda 2019 - Mukura Project",
    "Longitude": 3271396.7489,
    "Latitude": -218498.988
  },
  {
    "Project_Title": "Vietnam 2019 - Pleiku City Greenbelt",
    "Longitude": 12023492.6322,
    "Latitude": 1567284.8265
  },
  {
    "Project_Title": "Philippines 2019 - Mount Matutum",
    "Longitude": 13914432.673,
    "Latitude": 711039.1693
  },
  {
    "Project_Title": "British Columbia 2019 - Fall ",
    "Longitude": -13554444.3196,
    "Latitude": 6854545.2154
  },
  {
    "Project_Title": "Peru 2019 - Madre de Dios (Phase 1 continuation)",
    "Longitude": -7702587.19,
    "Latitude": -1411541.4531
  },
  {
    "Project_Title": "Peru 2019 - Madre de Dios (Phase 2)",
    "Longitude": -7702587.19,
    "Latitude": -1411541.4531
  },
  {},
  {
    "Project_Title": "Peru 2019 - Future of Forest Work and Communities",
    "Longitude": -8136898.4022,
    "Latitude": -416063.9374
  },
  {
    "Project_Title": "New York 2019 - Goetchius Wetland Preserve- W. Branch of Owego Creek",
    "Longitude": -8493613.2446,
    "Latitude": 5218529.4765
  },
  {
    "Project_Title": "Florida 2020 - Goethe State Forest  ",
    "Longitude": -9195141.7504,
    "Latitude": 3406028.0577
  },
  {
    "Project_Title": "Ontario 2019 - Preston Gravel Pit Rehabilitation ",
    "Longitude": -8714340.5421,
    "Latitude": 5536102.1202
  },
  {
    "Project_Title": "Oregon 2019 - Jones Fire Reforestation ",
    "Longitude": -13641725.2569,
    "Latitude": 5461107.2019
  },
  {
    "Project_Title": "Iowa - State Forest Spring Planting Projects 2019",
    "Longitude": -10344152.3976,
    "Latitude": 5021460.5418
  },
  {
    "Project_Title": "Bolivia 2019 - Amazon Lomerio Territory",
    "Longitude": -6876841.3598,
    "Latitude": -1887110.6031
  },
  {
    "Project_Title": "Tennessee 2019 - Hardwoods Restoration",
    "Longitude": -9342013.9325,
    "Latitude": 4295206.5724
  },
  {
    "Project_Title": "Illinois 2019 - Million Trees Project",
    "Longitude": -9892318.3843,
    "Latitude": 4819293.8455
  },
  {
    "Project_Title": "Andes 2019 - High Polylepis ",
    "Longitude": -7764110.8231,
    "Latitude": -2062595.3418
  },
  {
    "Project_Title": "California 2020 - Yosemite Valley Restoration",
    "Longitude": -13330147.1117,
    "Latitude": 4529836.188
  },
  {
    "Project_Title": "Ontario 2020 - Private Land Reforestation Program",
    "Longitude": -8411484.7355,
    "Latitude": 5638219.9583
  },
  {
    "Project_Title": "New England 2020 - Connecticut River Riparian Restoration",
    "Longitude": -8015554.5868,
    "Latitude": 5483101.9356
  },
  {
    "Project_Title": "California 2020 - RCD restoration Central Valley ",
    "Longitude": -13566481.0735,
    "Latitude": 4576880.7864
  },
  {
    "Project_Title": "Kentucky 2020 - Rush Island Bottoms Rehabilitation and Timberlake Restoration",
    "Longitude": -9561014.6591,
    "Latitude": 4476730.6487
  },
  {
    "Project_Title": "Kentucky 2020 - Appalachia/Daniel Boone National Forest ",
    "Longitude": -9399834.4014,
    "Latitude": 4439209.8366
  },
  {
    "Project_Title": "British Columbia 2020 - Spring",
    "Longitude": -13713174.8483,
    "Latitude": 6773589.126
  },
  {
    "Project_Title": "North Carolina 2020 - Mud Creek Confluence Floodplain Restoration ",
    "Longitude": -9185114.0372,
    "Latitude": 4197711.5276
  },
  {
    "Project_Title": " Uganda 2020 - Bwindi Forest Buffer",
    "Longitude": 3297294.5606,
    "Latitude": -117131.2742
  },
  {
    "Project_Title": "Haiti 2019 - Bois Blanc Communal Forest ",
    "Longitude": -8024909.3246,
    "Latitude": 2223774.8859
  },
  {
    "Project_Title": "Texas 2020 - Boggy Slough Conservation Area ",
    "Longitude": -10578385.4433,
    "Latitude": 3682578.2607
  },
  {
    "Project_Title": "Georgia 2020 - Tree Establishment Program",
    "Longitude": -9288627.665,
    "Latitude": 3928251.6315
  },
  {
    "Project_Title": "New Jersey 2020 - Magnolia Road Shelterwood",
    "Longitude": -8305389.4684,
    "Latitude": 4852146.7266
  },
  {
    "Project_Title": "Oregon 2020 - Orca Whale Project",
    "Longitude": -13590991.065,
    "Latitude": 5702973.3162
  },
  {
    "Project_Title": "Brazil 2020 - Mantiqueira Mountains",
    "Longitude": -5145632.0767,
    "Latitude": -2614317.3975
  },
  {
    "Project_Title": "South Carolina 2020 - Cheraw State Park Longleaf Reforestation Project ",
    "Longitude": -8894496.5551,
    "Latitude": 4115204.523
  },
  {
    "Project_Title": "California 2020 - Moonlight Fire Area Restoration Project",
    "Longitude": -13432656.6778,
    "Latitude": 4889259.8774
  },
  {
    "Project_Title": "Colorado 2020 - Black Mesa Diversity",
    "Longitude": -11969957.308,
    "Latitude": 4697960.4701
  },
  {
    "Project_Title": "California 2020 - CCI Blue Rush Reforestation",
    "Longitude": -13282931.5174,
    "Latitude": 4452277.2976
  },
  {
    "Project_Title": "California 2020 - Salmon August Reforestation, Klamath National Forest",
    "Longitude": -13652121.9407,
    "Latitude": 5061856.6485
  },
  {
    "Project_Title": "Florida 2020 - Twin Rivers State Forest ",
    "Longitude": -9266603.5079,
    "Latitude": 3573180.3498
  },
  {
    "Project_Title": "Florida 2020 - Peace River State Forest",
    "Longitude": -9125078.9917,
    "Latitude": 3142021.2109
  },
  {
    "Project_Title": "Arkansas 2020 - Ouachita Shortleaf Pine Planting",
    "Longitude": -10442258.7101,
    "Latitude": 4116327.3408
  },
  {
    "Project_Title": "Arkansas 2020 - Ozark Shortleaf planting",
    "Longitude": -10368177.4703,
    "Latitude": 4201867.0928
  },
  {
    "Project_Title": "Oregon 2020 - HK Fire Restoration",
    "Longitude": -13293319.407,
    "Latitude": 5631282.676
  },
  {
    "Project_Title": "California 2020 - Redwood Complex Fire Reforestation",
    "Longitude": -13711925.5764,
    "Latitude": 4770673.8004
  },
  {
    "Project_Title": "Colorado 2020 - Wolf Creek Reforestation",
    "Longitude": -11890168.6177,
    "Latitude": 4507772.5612
  },
  {
    "Project_Title": "Montana 2020 - Flathead NF Acquired Lands Restoration ",
    "Longitude": -12670749.2361,
    "Latitude": 6098710.5053
  },
  {
    "Project_Title": "Montana 2020 - Sheep Gap Fire Reforestation",
    "Longitude": -12845200.1252,
    "Latitude": 6065210.2544
  },
  {
    "Project_Title": "New Mexico 2020 - Scott Able Fire/Lincoln National Forest",
    "Longitude": -11760547.9799,
    "Latitude": 3871008.1588
  },
  {
    "Project_Title": "Oregon 2020 - South Fork Fire 2014",
    "Longitude": -13234601.2699,
    "Latitude": 5545593.8287
  },
  {
    "Project_Title": "Oregon 2020 - Umpqua North Fires Restoration Planting",
    "Longitude": -13627750.8759,
    "Latitude": 5350385.6539
  },
  {
    "Project_Title": "Indonesia 2020 - Lampung",
    "Longitude": 11638712.7268,
    "Latitude": -601541.2624
  },
  {
    "Project_Title": "Philippines 2020 - Mangrove Reforestation",
    "Longitude": 13864280.8935,
    "Latitude": 777790.1792
  },
  {
    "Project_Title": "Mexico 2020 - Asoc Forestal Palizada",
    "Longitude": -10210388.4851,
    "Latitude": 2038247.626
  },
  {
    "Project_Title": "Arkansas 2020 - Central Arkansas Water Forest Legacy ",
    "Longitude": -10320519.7695,
    "Latitude": 4147376.0943
  },
  {
    "Project_Title": "Scotland 2020 - Talla & Gameshope Native Woodland Restoration",
    "Longitude": -376492.314,
    "Latitude": 7452392.4325
  },
  {
    "Project_Title": "Rwanda 2020 - Kula Project",
    "Longitude": 3316883.5716,
    "Latitude": -200855.7799
  },
  {
    "Project_Title": "Uganda 2020 - Paibona Restoration, Northern Region ",
    "Longitude": 3611352.1459,
    "Latitude": 334934.7134
  },
  {
    "Project_Title": "Ghana 2020 - Tongo Hills",
    "Longitude": -85685.3494,
    "Latitude": 1199153.2776
  },
  {
    "Project_Title": "Papua New Guinea 2020 - Port Moresby Nature Park",
    "Longitude": 16382579.5688,
    "Latitude": -1051140.2916
  },
  {
    "Project_Title": "New Brunswick 2020 - Whaelghinbran and Spring Brook Restoration Forest",
    "Longitude": -7245403.0595,
    "Latitude": 5799848.4711
  },
  {
    "Project_Title": "Kenya 2020 - Kijabe Forest",
    "Longitude": 4073270.5718,
    "Latitude": -104998.8091
  },
  {
    "Project_Title": "Pennsylvania 2020 - The Keystone Tree Partnership",
    "Longitude": -8537896.0323,
    "Latitude": 4908036.5947
  },
  {
    "Project_Title": "Australia 2020 - Northern Rivers NSW (Koalas)",
    "Longitude": 16607736.5751,
    "Latitude": -2897197.836
  },
  {
    "Project_Title": "California 2020 - Restoring Paramount Ranch following the Woolsey Fire ",
    "Longitude": -13219700.8889,
    "Latitude": 4044894.2587
  },
  {
    "Project_Title": "Illinois 2020 - Living lands and water",
    "Longitude": -9831805.8883,
    "Latitude": 5134231.9429
  },
  {
    "Project_Title": "Missouri 2020 - Forest ReLeaf Potting Days ",
    "Longitude": -10073689.3382,
    "Latitude": 4679491.6026
  },
  {
    "Project_Title": "Indonesia 2020 - AZ Forest (Tanjung Puting)",
    "Longitude": 12458191.2585,
    "Latitude": -292376.1056
  },
  {
    "Project_Title": "Oklahoma 2020 - Seedling Program",
    "Longitude": -10677198.9407,
    "Latitude": 4315327.8203
  },
  {
    "Project_Title": "California 2020 - Lamb Ranch Wildfire Restoration ",
    "Longitude": -13692297.3676,
    "Latitude": 4736005.8538
  },
  {
    "Project_Title": "Philippines 2020 - Mindanao (BAMBOO)",
    "Longitude": 13911898.4403,
    "Latitude": 898856.0944
  },
  {
    "Project_Title": "Tennessee 2020 - Green Partnership with One Tree Planted ",
    "Longitude": -9638091.2727,
    "Latitude": 4234430.3849
  },
  {
    "Project_Title": "Mexico 2020 - SENDAS",
    "Longitude": -10810630.8661,
    "Latitude": 2227069.3809
  },
  {
    "Project_Title": "Rwanda 2020 - Eastern & Western Provinces",
    "Longitude": 3282194.0672,
    "Latitude": -223275.2719
  },
  {
    "Project_Title": "Brazil 2020 - OCT - Nestle",
    "Longitude": -4392112.7757,
    "Latitude": -1570690.4942
  },
  {
    "Project_Title": "Mexico 2020 - Reforestamos Mexico",
    "Longitude": -11088657.5138,
    "Latitude": 2289472.5991
  },
  {
    "Project_Title": "Brazil 2020 - Arboretum - Nestle",
    "Longitude": -4407670.6263,
    "Latitude": -1917974.8808
  },
  {
    "Project_Title": "Brazil 2020 - Natureza Bela - Nestle",
    "Longitude": -4377289.5191,
    "Latitude": -1855719.2944
  },
  {
    "Project_Title": "Australia 2020 - South West Catchments",
    "Longitude": 12876126.5165,
    "Latitude": -3944294.2338
  },
  {
    "Project_Title": "Quebec 2020 - Abitibi",
    "Longitude": -8795006.6526,
    "Latitude": 6123561.0986
  },
  {
    "Project_Title": "Florida 2020 - Etoniah Creek State Forest Reforestation",
    "Longitude": -9107227.1781,
    "Latitude": 3469695.9096
  },
  {
    "Project_Title": "(to delete) Australia 2020 - Bushfire Recovery Nurseries",
    "Longitude": 15379768.7563,
    "Latitude": -4253354.6882
  },
  {
    "Project_Title": "Tanzania 2020 - Phase 1",
    "Longitude": 3919791.5946,
    "Latitude": -682006.3959
  },
  {
    "Project_Title": "India 2020 - Fruit Tree & Mangrove Project\n",
    "Longitude": 9895309.2719,
    "Latitude": 2459261.4914
  },
  {
    "Project_Title": "Honduras 2020 - Cordillera Nombre de Dios Mountains",
    "Longitude": -9647732.5425,
    "Latitude": 1765878.53
  },
  {
    "Project_Title": "Idaho 2020 - Nez Perce Clearwater National Forest Planting 1",
    "Longitude": -12841054.3647,
    "Latitude": 5809796.7484
  },
  {
    "Project_Title": "Idaho 2020 - Nez Perce Clearwater National Forest Planting 2",
    "Longitude": -12841054.3647,
    "Latitude": 5809796.7484
  },
  {
    "Project_Title": "Florida 2021 - Blackwater River State Forest Yellow River",
    "Longitude": -9669495.2213,
    "Latitude": 3584639.3067
  },
  {
    "Project_Title": "Uganda 2020 - Albertine Rift",
    "Longitude": 3479759.2864,
    "Latitude": 165088.9083
  },
  {
    "Project_Title": "Brazil 2020 - Araguaia Biodiversity Corridor",
    "Longitude": -5576825.4516,
    "Latitude": -1028119.393
  },
  {
    "Project_Title": "Ontario 2020 - Forest Habitat Enhancement in the Otonabee Region Watershed",
    "Longitude": -8719129.0613,
    "Latitude": 5505481.7416
  },
  {
    "Project_Title": "England 2020 – Saving Devon's Treescapes",
    "Longitude": -381402.9507,
    "Latitude": 6567271.9753
  },
  {
    "Project_Title": "Haiti 2020 - Artibonite",
    "Longitude": -8143404.5811,
    "Latitude": 2230383.2261
  },
  {
    "Project_Title": "Indonesia 2020 - Bukit Tigapuluh (Orangutans)",
    "Longitude": 11441350.1492,
    "Latitude": -137913.9242
  },
  {
    "Project_Title": "New Zealand 2020 - Waingake Native Restoration (Pamoa Forest)",
    "Longitude": 19789224.4675,
    "Latitude": -4697359.124
  },
  {
    "Project_Title": "Ethiopia 2020 - Gullele Botanic Garden ",
    "Longitude": 4310393.8767,
    "Latitude": 1014859.1618
  },
  {
    "Project_Title": "Spain 2020 - Undabaso Basoa",
    "Longitude": -297567.2703,
    "Latitude": 5347736.3048
  },
  {
    "Project_Title": "Vietnam 2020 - Rurality smallholder restoration project",
    "Longitude": 11988648.4293,
    "Latitude": 1192963.9047
  },
  {
    "Project_Title": "New York 2020 - Birdseye Hollow State Forest",
    "Longitude": -8591871.4236,
    "Latitude": 5210950.5325
  },
  {
    "Project_Title": "New York 2020 - Butternut Creek at Bailey Rd",
    "Longitude": -8379660.587,
    "Latitude": 5237570.7354
  },
  {
    "Project_Title": "New York 2020 - W. Branch Owego Creek",
    "Longitude": -8492709.3759,
    "Latitude": 5223772.193
  },
  {
    "Project_Title": "Nova Scotia 2020 - Antigonish County Community Reforestation",
    "Longitude": -6917948.6845,
    "Latitude": 5713795.9739
  },
  {
    "Project_Title": "Mexico 2020 – Sierra Gorda Biosphere Reserve ",
    "Longitude": -11090267.2771,
    "Latitude": 3019874.8579
  },
  {
    "Project_Title": "Montana 2020 - Woods Pass Whitebark Pine Planting",
    "Longitude": -12733862.4893,
    "Latitude": 5703690.9337
  },
  {
    "Project_Title": "Australia 2020 - AZ Forest",
    "Longitude": 16702177.3928,
    "Latitude": -4108494.0237
  },
  {
    "Project_Title": "Indonesia 2020 - AZ Forest (Citarum River) ",
    "Longitude": 11943232.2812,
    "Latitude": -702616.5791
  },
  {
    "Project_Title": "Brazil 2020 - Atlantic Forest Restoration",
    "Longitude": -5343364.0559,
    "Latitude": -2773709.9021
  },
  {
    "Project_Title": "British Columbia 2020 - DroneSeed ",
    "Longitude": -14209668.1707,
    "Latitude": 7118559.6877
  },
  {
    "Project_Title": "Andes 2020 - High Andes Polylepis Forest",
    "Longitude": -7764110.8231,
    "Latitude": -2062595.3418
  },
  {
    "Project_Title": "Ecuador 2020 - Amazon, Sapara Territory, Pastaza",
    "Longitude": -8610201.2698,
    "Latitude": -115309.0056
  },
  {
    "Project_Title": "Peru 2020 - Loreto",
    "Longitude": -8511751.7593,
    "Latitude": -728680.1774
  },
  {
    "Project_Title": "Peru 2020 - Ucayali",
    "Longitude": -8269000.8489,
    "Latitude": -938054.4112
  },
  {
    "Project_Title": "Michigan 2021 - Spruce Salvage Planting",
    "Longitude": -9467258.8236,
    "Latitude": 5799302.4557
  },
  {
    "Project_Title": "Michigan 2021 - White Pine Diversity Planting",
    "Longitude": -9443183.3121,
    "Latitude": 5761055.0365
  },
  {
    "Project_Title": "Florida 2021 - Apalachicola Longleaf",
    "Longitude": -9108123.2655,
    "Latitude": 3397407.2232
  },
  {
    "Project_Title": "California 2021 - Cove Fire Salvage",
    "Longitude": -13470636.4056,
    "Latitude": 5051970.7012
  },
  {
    "Project_Title": "Peru 2021 - Madre de Dios (Phase 4)",
    "Longitude": -7702587.19,
    "Latitude": -1411541.4531
  },
  {
    "Project_Title": "Maryland 2021 - Washington County-Allegany County",
    "Longitude": -8676746.8948,
    "Latitude": 4807287.9121
  },
  {
    "Project_Title": "Philippines 2021 - Mount Matutum",
    "Longitude": 13919456.3769,
    "Latitude": 708796.3083
  },
  {
    "Project_Title": "Minnesota 2021 - Chippewa National Forest",
    "Longitude": -10476430.4542,
    "Latitude": 6009085.2589
  },
  {
    "Project_Title": "Maine 2021 - Bethel Community Forest Restoration",
    "Longitude": -7885542.7312,
    "Latitude": 5533604.1931
  },
  {
    "Project_Title": "Oregon 2021 - Orca Whale Project",
    "Longitude": -13590991.065,
    "Latitude": 5702973.3162
  },
  {
    "Project_Title": "Australia 2021 - One Million Trees in Southwest Western Australia",
    "Longitude": 13130010.0961,
    "Latitude": -4063228.1656
  },
  {
    "Project_Title": "Arkansas 2021 - Central Arkansas Water Forest Legacy (Year 2)",
    "Longitude": -10320519.7695,
    "Latitude": 4147376.0943
  },
  {
    "Project_Title": "Oklahoma 2021 - Seedling Program",
    "Longitude": -10677198.9407,
    "Latitude": 4315327.8203
  },
  {
    "Project_Title": "Georgia 2021 - Tree Establishment Program (Year 2)",
    "Longitude": -9440777.8092,
    "Latitude": 4044389.7233
  },
  {
    "Project_Title": "Brazil 2020 - Corridors for Life",
    "Longitude": -5831800.9897,
    "Latitude": -2559393.9065
  },
  {
    "Project_Title": "North Carolina 2021 - Mud Creek Confluence Floodplain Restoration  ",
    "Longitude": -9187194.5695,
    "Latitude": 4218453.0425
  },
  {
    "Project_Title": "Scotland 2021 - Restoring Woodland in the Wild Heart of Southern Scotland",
    "Longitude": -380515.662,
    "Latitude": 7446055.6827
  },
  {
    "Project_Title": "Texas 2021 - Pine Island Reforestation",
    "Longitude": -10568495.901,
    "Latitude": 3678494.629
  },
  {
    "Project_Title": "Brazil 2021 - Mantiqueira Mountains",
    "Longitude": -5178057.8481,
    "Latitude": -2582283.9878
  },
  {
    "Project_Title": "California 2021 - Redwood Complex Fire Reforestation",
    "Longitude": -13714374.6943,
    "Latitude": 4759586.7793
  },
  {
    "Project_Title": "California 2021 - Moonlight Fire Area Restoration Project ",
    "Longitude": -13431226.8346,
    "Latitude": 4893960.6929
  },
  {
    "Project_Title": "Michigan 2021 – Rebuilding the Urban Forest",
    "Longitude": -9268508.1254,
    "Latitude": 5215601.7124
  },
  {
    "Project_Title": "California 2021 - RCD restoration project",
    "Longitude": -13445054.8861,
    "Latitude": 4681434.8016
  },
  {
    "Project_Title": "Australia 2021 - Bushfire Recovery Nurseries",
    "Longitude": 15379768.7563,
    "Latitude": -4253354.6882
  },
  {
    "Project_Title": "California 2021 - Yosemite Valley Restoration ",
    "Longitude": -13330819.5482,
    "Latitude": 4530071.3983
  },
  {
    "Project_Title": "Iceland 2021 - Dragon's Nest Forest",
    "Longitude": -1531685.3941,
    "Latitude": 9644615.3818
  },
  {
    "Project_Title": "New England 2021 - Connecticut River Riparian Restoration (Phase 1)",
    "Longitude": -8025675.7482,
    "Latitude": 5478259.9477
  },
  {
    "Project_Title": "Haiti 2021 - MSPJ Mangrove Rehabilitation ",
    "Longitude": -8045100.5652,
    "Latitude": 2234692.8856
  },
  {
    "Project_Title": "Tennessee 2021 - East TN Nursery Seedlings ",
    "Longitude": -9414134.3797,
    "Latitude": 4197485.6484
  },
  {
    "Project_Title": "California 2021 - Restoring Paramount Ranch following the Woolsey Fire  ",
    "Longitude": -13219700.8889,
    "Latitude": 4044894.2587
  },
  {
    "Project_Title": "California 2021 - Rancho Sierra Vista Potrero Restoration ",
    "Longitude": -13242193.9939,
    "Latitude": 4049726.9679
  },
  {
    "Project_Title": "California 2021 - Rancho Sierra Vista Yerba Mansa Restoration",
    "Longitude": 12238723.5688,
    "Latitude": 102630.4515
  },
  {
    "Project_Title": "California 2021 - Cheeseboro Canyon Restoration",
    "Longitude": -13216971.1792,
    "Latitude": 4049342.4711
  },
  {
    "Project_Title": "Ontario 2021 - Grey Sauble Tree Planting",
    "Longitude": -9006199.2221,
    "Latitude": 5559564.9815
  },
  {
    "Project_Title": "Costa Rica 2021 - Reforesting the Tropical Dry Forest",
    "Longitude": -9526758.7085,
    "Latitude": 1204015.8195
  },
  {
    "Project_Title": "Uganda 2021 - Paicho Nursery Hub ",
    "Longitude": 3617983.429,
    "Latitude": 332585.0923
  },
  {
    "Project_Title": "Ghana 2021 - Western Region",
    "Longitude": -196560.4728,
    "Latitude": 585611.9911
  },
  {
    "Project_Title": "South Carolina 2021 - Longleaf Restoration",
    "Longitude": -8846260.7066,
    "Latitude": 3906986.605
  },
  {
    "Project_Title": "Alabama 2021 - Longleaf Restoration",
    "Longitude": -9471251.1491,
    "Latitude": 3647255.0944
  },
  {
    "Project_Title": "Rwanda 2021 - Kula Coffee Tree Seedling Nurseries ",
    "Longitude": 3316883.5716,
    "Latitude": -200855.7799
  },
  {
    "Project_Title": "India 2021 - Fruit Trees",
    "Longitude": 8455087.7818,
    "Latitude": 2972522.1357
  },
  {
    "Project_Title": "Australia 2021 - Mornington Peninsula Koalas",
    "Longitude": 16156100.3988,
    "Latitude": -4633439.7138
  },
  {
    "Project_Title": "Scotland 2021 - Talla & Gameshope Native Woodland Restoration",
    "Longitude": -376492.314,
    "Latitude": 7452392.4325
  },
  {
    "Project_Title": "Ontario 2021 - Planting Trees in Rural Ottawa",
    "Longitude": -8411484.7355,
    "Latitude": 5638219.9583
  },
  {
    "Project_Title": "Australia 2021 - Northern Rivers NSW (Koalas)",
    "Longitude": 16607736.5751,
    "Latitude": -2897197.836
  },
  {
    "Project_Title": "Germany 2021 - Klimawald – Stift Ehreshoven",
    "Longitude": 824066.7982,
    "Latitude": 6616369.5651
  },
  {
    "Project_Title": "Australia 2021 - AZ Forest",
    "Longitude": 16702177.3928,
    "Latitude": -4108494.0237
  },
  {
    "Project_Title": "California 2021 - Cranston Fire Reforestation",
    "Longitude": -12990018.7454,
    "Latitude": 3990417.9046
  },
  {
    "Project_Title": "California 2021 - Sawmill Liebre Reforestation Project",
    "Longitude": -13188403.5588,
    "Latitude": 4116740.062
  },
  {
    "Project_Title": "Colorado 2021 - Cathedral Salvage Planting ",
    "Longitude": -11906955.3742,
    "Latitude": 4587707.3382
  },
  {
    "Project_Title": "Idaho 2021 - Salmon River and Red River RD Spring Planting ",
    "Longitude": -12897105.3424,
    "Latitude": 5737700.0412
  },
  {
    "Project_Title": "Arizona 2021 - Coconino Post-Fire Community-Based Reforestation",
    "Longitude": -12427690.898,
    "Latitude": 4195103.5897
  },
  {
    "Project_Title": "South Carolina 2021 - Andrew Pickens Reforestation ",
    "Longitude": -9259626.1692,
    "Latitude": 4138356.8095
  },
  {
    "Project_Title": "Oregon 2021 - Replanting within Canyon Mountain Fire Complex and Rail Fire",
    "Longitude": -13215500.2925,
    "Latitude": 5537292.8973
  },
  {
    "Project_Title": "Washington 2021 - Cougar Creek Wildfire Reforestation",
    "Longitude": -13410585.585,
    "Latitude": 6074209.6997
  },
  {
    "Project_Title": "Kentucky 2021 - Wildcat Ridge",
    "Longitude": -9398259.3297,
    "Latitude": 4437294.9098
  },
  {
    "Project_Title": "Texas 2021- NFGT Reforestation ",
    "Longitude": -10594275.9388,
    "Latitude": 3644182.8997
  },
  {
    "Project_Title": "Minnesota 2021 - Chippewa Forest Restoration Planting",
    "Longitude": -10459932.8912,
    "Latitude": 6035608.8666
  },
  {
    "Project_Title": "Michigan 2021 - Hiawatha restoration ",
    "Longitude": -9453817.3291,
    "Latitude": 5784599.7672
  },
  {
    "Project_Title": "Chile 2021 - Trees & Seas",
    "Longitude": -8184585.4456,
    "Latitude": -5144394.3211
  },
  {
    "Project_Title": "Guatemala 2021 - Laguna Brava",
    "Longitude": -10193535.8464,
    "Latitude": 1807527.7631
  },
  {
    "Project_Title": "Ethiopia 2021 - Amhara Region",
    "Longitude": 4162490.0145,
    "Latitude": 1227140.7983
  },
  {
    "Project_Title": "Australia 2021 - Project Platypus",
    "Longitude": 15897920.3988,
    "Latitude": -4451408.9829
  },
  {
    "Project_Title": "Pennsylvania 2021 - Reforestation of “Legacy” surface mined lands in Appalachia",
    "Longitude": -8973371.2089,
    "Latitude": 5041619.0961
  },
  {
    "Project_Title": "Italy 2021 - Regenerative Agroforestry Project ",
    "Longitude": 1021487.2397,
    "Latitude": 5705957.7571
  },
  {
    "Project_Title": "British Columbia 2021 - Hanceville Fire Restoration",
    "Longitude": -13675212.0076,
    "Latitude": 6769008.1994
  },
  {
    "Project_Title": "British Columbia 2021 - Old Growth Management Areas",
    "Longitude": -13779680.1845,
    "Latitude": 6951207.9855
  },
  {
    "Project_Title": "New Brunswick 2021 - Chignecto Isthmus Restoration Forest",
    "Longitude": -7146851.6683,
    "Latitude": 5780998.5751
  },
  {
    "Project_Title": "Quebec 2021 - Abitibi ",
    "Longitude": -8795006.6526,
    "Latitude": 6123561.0986
  },
  {
    "Project_Title": "Ethiopia 2021 - Tree planting in Gullele Botanic Garden ",
    "Longitude": 4310399.8879,
    "Latitude": 1014808.9963
  },
  {
    "Project_Title": "Denmark 2021 - Jutland",
    "Longitude": 985518.1312,
    "Latitude": 7649356.4187
  },
  {
    "Project_Title": "South Africa 2021 - Cape Town ",
    "Longitude": 2094472.4344,
    "Latitude": -4042505.5643
  },
  {
    "Project_Title": "Vietnam 2021 - Xuan Lien Nature Reserve",
    "Longitude": 11720563.1209,
    "Latitude": 2257196.0198
  },
  {
    "Project_Title": "Brazil 2021/2022 - Natureza Bela - Nestle",
    "Longitude": -4370468.9984,
    "Latitude": -1867000.2289
  },
  {
    "Project_Title": "Brazil 2021/2022 - OCT - Nestle",
    "Longitude": -4392112.7757,
    "Latitude": -1570690.4942
  },
  {
    "Project_Title": "Brazil 2021/2022 - Arboretum - Nestle",
    "Longitude": -4409984.6034,
    "Latitude": -1940341.9036
  },
  {
    "Project_Title": "Brazil 2021 - Raízes do Mogi Guaçu",
    "Longitude": -5166978.2147,
    "Latitude": -2578003.8365
  },
  {
    "Project_Title": "Peru 2021 - San Martin",
    "Longitude": -8570736.9596,
    "Latitude": -775344.6443
  },
  {
    "Project_Title": "Guatemala 2021 - San Marcos Mangrove Restoration",
    "Longitude": -10255887.396,
    "Latitude": 1629531.3364
  },
  {
    "Project_Title": "England 2021 – Saving Devon's Treescapes ",
    "Longitude": -381402.9507,
    "Latitude": 6567271.9753
  },
  {
    "Project_Title": "Utah 2022 - Utah Ecological Restoration Plantings",
    "Longitude": -12462073.8152,
    "Latitude": 4954423.2065
  },
  {
    "Project_Title": "British Columbia 2021 - Hanceville Fire Restoration (2)",
    "Longitude": -13683682.6973,
    "Latitude": 6771628.0133
  },
  {
    "Project_Title": "British Columbia 2021 - Old Growth Management Areas (2)",
    "Longitude": -13732525.5933,
    "Latitude": 6868963.0944
  },
  {
    "Project_Title": "Malawi 2021 - Planting indigenous trees",
    "Longitude": 3739361.6243,
    "Latitude": -1335004.3862
  },
  {
    "Project_Title": "Côte d’Ivoire 2021 - Trees for Cocoa Farms and Degraded Forest Reserves",
    "Longitude": -601311.8841,
    "Latitude": 642118.8393
  },
  {
    "Project_Title": "Brazil 2021 - Corridors for Life",
    "Longitude": -5835283.9072,
    "Latitude": -2581044.0771
  },
  {
    "Project_Title": "Indonesia 2021 - AZ Forest (Citarum River)",
    "Longitude": 11943232.2812,
    "Latitude": -702616.5791
  },
  {
    "Project_Title": "Brazil 2021 - Planting Forests, Harvesting Water",
    "Longitude": -4867060.9688,
    "Latitude": -2120525.7455
  },
  {
    "Project_Title": "Indonesia 2021 - Bangka Agroforestry",
    "Longitude": 11820881.4296,
    "Latitude": -260914.4113
  },
  {
    "Project_Title": "Sri Lanka 2021 - Knuckles Mountain Range",
    "Longitude": 9004610.1452,
    "Latitude": 842167.9281
  },
  {
    "Project_Title": "Sri Lanka 2021 - Mangroves (North Coast)",
    "Longitude": 8904879.5533,
    "Latitude": 1004513.8405
  },
  {
    "Project_Title": "Ghana 2021 - North Bandai Forest Reserve",
    "Longitude": -90253.8356,
    "Latitude": 764888.6541
  },
  {
    "Project_Title": "Illinois 2021 – Million Trees Project",
    "Longitude": -9892318.3843,
    "Latitude": 4819293.8455
  },
  {
    "Project_Title": "Philippines 2021 - Indigenous Bamboo Reforestation",
    "Longitude": 13911898.4403,
    "Latitude": 898856.0944
  },
  {
    "Project_Title": "India 2021 - Sand Dunes & Biodiversity",
    "Longitude": 8611281.6255,
    "Latitude": 907998.9967
  },
  {
    "Project_Title": "Washington 2021 - Spokane River Restoration Community Plantings",
    "Longitude": -13036026.7793,
    "Latitude": 6073779.2999
  },
  {
    "Project_Title": "California 2021 - Tahoe Fire restoration",
    "Longitude": -13368085.8072,
    "Latitude": 4716922.0837
  },
  {
    "Project_Title": "Indonesia 2021 - Climate-Smart Agroforestry",
    "Longitude": 11791207.1488,
    "Latitude": -701108.8016
  },
  {
    "Project_Title": "California 2021 - Camp Fire Restoration in Northern California",
    "Longitude": -13518653.2331,
    "Latitude": 4820034.9676
  },
  {
    "Project_Title": "Costa Rica 2021 - Ridge to Reef Restoration",
    "Longitude": -9302038.3241,
    "Latitude": 954032.1194
  },
  {
    "Project_Title": "Indonesia 2021 - Restoration Forest with Agroforestry",
    "Longitude": 13051587.3628,
    "Latitude": 201794.3823
  },
  {
    "Project_Title": "Romania 2021 - The story of the oak forests of Ciuc",
    "Longitude": 2859960.4676,
    "Latitude": 5868551.5115
  },
  {
    "Project_Title": "California 2021 - Mendocino and Sonoma Counties Restoration (Phase 1)",
    "Longitude": -13696036.0327,
    "Latitude": 4675963.6618
  },
  {
    "Project_Title": "Hawaii 2021 - Mauna Kea",
    "Longitude": -17323571.8073,
    "Latitude": 2252895.4844
  },
  {
    "Project_Title": "Nova Scotia 2021 - Victoria Municipal Park",
    "Longitude": -7042146.7962,
    "Latitude": 5674700.9888
  },
  {
    "Project_Title": "Prince Edward Island 2021 - PEI National Park",
    "Longitude": -6979998.7731,
    "Latitude": 5852147.051
  },
  {
    "Project_Title": "Jamaica 2021 - Blue and John Crow Mountains National Park",
    "Longitude": -8541917.6715,
    "Latitude": 2047554.6183
  },
  {
    "Project_Title": "Australia 2021 - South West Catchments",
    "Longitude": 12876126.5165,
    "Latitude": -3944294.2338
  },
  {
    "Project_Title": "Romania 2021 - Reviving the Carpathians",
    "Longitude": 2758868.0097,
    "Latitude": 5674151.4854
  },
  {
    "Project_Title": "Kenya 2021 - Kijabe Forest Trust",
    "Longitude": 4073270.5718,
    "Latitude": -104998.8091
  },
  {
    "Project_Title": "Mexico 2021/2022 - Nestle - SENDAS",
    "Longitude": -10812484.5059,
    "Latitude": 2226565.626
  },
  {
    "Project_Title": "California 2021 - Kincade Reforestation",
    "Longitude": -13664705.4959,
    "Latitude": 4683538.7116
  },
  {
    "Project_Title": "Andes 2021 - High Andes Polylepis Forest",
    "Longitude": -7764110.8231,
    "Latitude": -2062595.3418
  },
  {
    "Project_Title": "Peru 2021 - Ucayali",
    "Longitude": -8269000.8489,
    "Latitude": -938054.4112
  },
  {
    "Project_Title": "Brazil 2021 – Reforestation of a Degraded Area",
    "Longitude": -4938380.6314,
    "Latitude": -2593907.9753
  },
  {
    "Project_Title": "Brazil 2021 - Restoration of an Urban Forest Mosaic",
    "Longitude": -5181961.3696,
    "Latitude": -2586740.9352
  },
  {
    "Project_Title": "Haiti 2021 - Microwatersheds Restoration",
    "Longitude": -8035905.0187,
    "Latitude": 2221648.1081
  },
  {
    "Project_Title": "Rwanda 2021 - Promoting landscape restoration Rwanda ",
    "Longitude": 3330651.446,
    "Latitude": -240738.0054
  },
  {
    "Project_Title": "Ireland 2022 - Humphreystown Wood",
    "Longitude": -729121.288,
    "Latitude": 7003222.2155
  },
  {
    "Project_Title": "Italy 2021 - Dosolo",
    "Longitude": 1182099.5577,
    "Latitude": 5610474.8081
  },
  {
    "Project_Title": "Honduras 2021 - Cordillera Nombre de Dios Mountains ",
    "Longitude": -9647732.5425,
    "Latitude": 1765878.53
  },
  {
    "Project_Title": "New Zealand 2021 - Papakura Stream Restoration",
    "Longitude": 19478377.1904,
    "Latitude": -4439645.8137
  },
  {
    "Project_Title": "Mexico 2021 - Jalisco and Querétaro",
    "Longitude": -381402.9507,
    "Latitude": 6567271.9753
  },
  {
    "Project_Title": "Thailand 2021 - Baan Cha Niang Community Reforestation",
    "Longitude": 11529907.999,
    "Latitude": 1712128.9222
  },
  {
    "Project_Title": "Guatemala 2021 - Agroforestry for Coffee Growing Communities in Sololá",
    "Longitude": -10151716.7315,
    "Latitude": 1650784.4825
  },
  {
    "Project_Title": "Indonesia 2021 - Community-Based Reforestation in North Sumatra",
    "Longitude": 10925161.6593,
    "Latitude": 384842.3633
  },
  {
    "Project_Title": "Cameroon 2021 - Reforestation Project in Kadey and Lom and Djerem",
    "Longitude": 1582710.9826,
    "Latitude": 605530.3245
  },
  {
    "Project_Title": "Kenya 2021 - Agroforestry and Community Development in Kitui",
    "Longitude": 4237953.5485,
    "Latitude": -163645.0327
  },
  {
    "Project_Title": "British Columbia 2021 - 2 Million Trees for Forest Fire Recovery",
    "Longitude": -13700750.4465,
    "Latitude": 6844537.2058
  },
  {
    "Project_Title": "Ontario 2021 - Larose Forest",
    "Longitude": -8367257.8446,
    "Latitude": 5681416.7418
  },
  {
    "Project_Title": "Vietnam 2021 - Riparian Restoration & Sustainable Livelihoods",
    "Longitude": 11983451.3453,
    "Latitude": 1190496.6195
  },
  {
    "Project_Title": "India 2021 - Plant for Punjab",
    "Longitude": 8450545.8542,
    "Latitude": 3502767.0548
  },
  {
    "Project_Title": "India 2021 - Sundarban Mangrove Project",
    "Longitude": -8196357.5208,
    "Latitude": 2227859.298
  },
  {
    "Project_Title": "Indonesia 2021 - Sumatra Gunung Leuser National Park Buffer Zone",
    "Longitude": 10931455.3293,
    "Latitude": 376805.4852
  },
  {
    "Project_Title": "Ontario 2021 - Red Lake Forest",
    "Longitude": -10441678.1611,
    "Latitude": 6620978.8851
  },
  {
    "Project_Title": "New Zealand 2021 - Waingake Native Restoration",
    "Longitude": 19789436.3975,
    "Latitude": -4699589.768
  },
  {
    "Project_Title": "Uganda 2021 - Palorinya Refugee Settlement ",
    "Longitude": 3512226.5598,
    "Latitude": 361008.5736
  },
  {
    "Project_Title": "Mexico 2021 - La Palizada - Restoring the Land of the Jaguar",
    "Longitude": -10240802.9159,
    "Latitude": 2048703.6965
  },
  {
    "Project_Title": "Australia 2021 - Bee Friendly Farming Launch",
    "Longitude": 15810849.2097,
    "Latitude": -4521345.6733
  },
  {
    "Project_Title": "Uganda 2021 - People of the World Forests",
    "Longitude": 3824066.7845,
    "Latitude": 115396.0929
  },
  {
    "Project_Title": "Thailand 2021 - Agroforestry with Smallholder Rubber Farmers",
    "Longitude": 11060003.2924,
    "Latitude": 1004591.849
  },
  {
    "Project_Title": "Spain 2021 - Undabaso Forest",
    "Longitude": -297567.2703,
    "Latitude": 5347736.3048
  },
  {
    "Project_Title": "Ghana 2021 - Cocoa Agroforestry",
    "Longitude": -154014.7189,
    "Latitude": 711701.6767
  },
  {
    "Project_Title": "New York 2021 - Mussel Flats",
    "Longitude": -8378269.2737,
    "Latitude": 5239043.7558
  },
  {
    "Project_Title": "Costa Rica 2021 - Puntarenas y Guanacaste ",
    "Longitude": -9467100.75,
    "Latitude": 1083101.0275
  },
  {
    "Project_Title": "Haiti 2021 - Restoring Watersheds & Reversing Poverty",
    "Longitude": -8051668.561,
    "Latitude": 2164314.0145
  },
  {
    "Project_Title": "England 2021 - Essex Forest Initiative",
    "Longitude": 63427.3645,
    "Latitude": 6765942.2745
  },
  {
    "Project_Title": "Mexico 2021 - Reserva de la Mariposa Monarca ",
    "Longitude": -11155112.8842,
    "Latitude": 2213516.5795
  },
  {
    "Project_Title": "British Columbia 2021 - Yunesit'in Fire Guard Rehabilitation",
    "Longitude": -13747643.192,
    "Latitude": 6777064.9034
  },
  {
    "Project_Title": "Ontario 2021 - Otonabee Region Tree Planting ",
    "Longitude": -8713070.4468,
    "Latitude": 5504462.6659
  },
  {
    "Project_Title": "United Arab Emirates 2021 - Reforesting Dubai Mangrove Sanctuary",
    "Longitude": 6113536.3987,
    "Latitude": 2866670.9713
  },
  {
    "Project_Title": "Prince Edward Island 2021 - PEI National Park SCALE",
    "Longitude": -7035959.9928,
    "Latitude": 5849188.1503
  },
  {
    "Project_Title": "England 2022 - Nationwide Community Planting",
    "Longitude": -181052.9431,
    "Latitude": 7118781.2204
  },
  {
    "Project_Title": "Brazil 2021 - Forests4Water",
    "Longitude": -4735850.0453,
    "Latitude": -2380530.2252
  },
  {
    "Project_Title": "California 2021 - Chester Reforestation",
    "Longitude": -13508481.0807,
    "Latitude": 4909175.9083
  },
  {
    "Project_Title": "Philippines 2021 - Community-Based Mangrove Reforestation",
    "Longitude": 13442095.4463,
    "Latitude": 1662697.7246
  },
  {
    "Project_Title": "Philippines 2021 - Mangrove Reforestation",
    "Longitude": 13864280.8935,
    "Latitude": 777790.1792
  },
  {
    "Project_Title": "Ohio 2022 - Sugar Island Preserve Restoration Project",
    "Longitude": -8997236.2253,
    "Latitude": 5085552.0266
  },
  {
    "Project_Title": "Brazil 2021 - Make the Forest Flourish I",
    "Longitude": -7882755.2255,
    "Latitude": -1008703.242
  },
  {
    "Project_Title": "Colombia 2022 - Chocó Analog Forestry",
    "Longitude": -8508731.7728,
    "Latitude": 592173.9512
  },
  {
    "Project_Title": "Tanzania 2021/2022 - Phase 2",
    "Longitude": 3977847.6034,
    "Latitude": -690257.3768
  },
  {
    "Project_Title": "Montana 2022 - Kootenai National Forest Planting",
    "Longitude": -12843565.5098,
    "Latitude": 6207000.7453
  },
  {
    "Project_Title": "Uganda 2022 - Albertine Rift",
    "Longitude": 3479759.2864,
    "Latitude": 165088.9083
  },
  {
    "Project_Title": "Chile 2022 - Torres del Paine National Park",
    "Longitude": -8123454.5031,
    "Latitude": -6642350.8918
  },
  {
    "Project_Title": "Australia 2022 - Bushfire Recovery Nurseries",
    "Longitude": 15379768.7563,
    "Latitude": -4253354.6882
  },
  {
    "Project_Title": "New Jersey 2022 - Magnolia Road Shelterwood ",
    "Longitude": -8305389.4684,
    "Latitude": 4852146.7266
  },
  {
    "Project_Title": "Australia 2022 - AZ Forest",
    "Longitude": 16702177.3928,
    "Latitude": -4108494.0237
  },
  {
    "Project_Title": "Denmark 2022 - Jutland",
    "Longitude": 973336.4393,
    "Latitude": 7649356.4187
  },
  {
    "Project_Title": "Mexico 2021/2022 - Nestle - Reforestamos Mexico",
    "Longitude": -10363811.7536,
    "Latitude": 1901257.4657
  },
  {
    "Project_Title": "Brazil 2022 - Raízes do Mogi Guaçu",
    "Longitude": -5162368.5826,
    "Latitude": -2576756.5132
  },
  {
    "Project_Title": "Scotland 2022 - Restoring Woodland in the Wild Heart of Southern Scotland",
    "Longitude": -380515.662,
    "Latitude": 7446055.6827
  },
  {
    "Project_Title": "Iceland 2022 - Dragon's Nest Forest",
    "Longitude": -1592536.6353,
    "Latitude": 9705570.1158
  },
  {
    "Project_Title": "Pennsylvania 2022 - The Keystone Tree Partnership",
    "Longitude": -8700818.637,
    "Latitude": 5002040.1983
  },
  {
    "Project_Title": "Côte d’Ivoire 2022 - Trees for Cocoa Farms and Degraded Forest Reserves ",
    "Longitude": -601311.8841,
    "Latitude": 642118.8393
  },
  {
    "Project_Title": "Indonesia 2022 - AZ Forest (Citarum River)",
    "Longitude": 11943232.2812,
    "Latitude": -702616.5791
  },
  {
    "Project_Title": "Indonesia 2022 - Climate-Smart Agroforestry",
    "Longitude": 11791207.1488,
    "Latitude": -701108.8016
  },
  {
    "Project_Title": "New England 2022 - Connecticut River Riparian Restoration (Phase 2)",
    "Longitude": -8025675.7482,
    "Latitude": 5478259.9477
  },
  {
    "Project_Title": "California 2022 - Carr Fire Wildfire Restoration ",
    "Longitude": -13648475.181,
    "Latitude": 4984925.9058
  },
  {
    "Project_Title": "California 2021 - Slater Fire Restoration ",
    "Longitude": -13734831.5431,
    "Latitude": 5137121.3137
  },
  {
    "Project_Title": "Romania 2022 - Reviving the Carpathians",
    "Longitude": 2758868.0097,
    "Latitude": 5674151.4854
  },
  {
    "Project_Title": "Romania 2022 - The story of the oak forests of Ciuc",
    "Longitude": 2859960.4676,
    "Latitude": 5868551.5115
  },
  {
    "Project_Title": "Ecuador 2022 - Ecosystems and food sovereignty in the Amazon",
    "Longitude": -8538420.4584,
    "Latitude": 4780.8386
  },
  {
    "Project_Title": "Iceland 2022 - Seer Hill",
    "Longitude": -2256058.1745,
    "Latitude": 9831719.5198
  },
  {
    "Project_Title": "Ontario 2022 - Larose Forest",
    "Longitude": -8367257.8446,
    "Latitude": 5681416.7418
  },
  {
    "Project_Title": "Bhutan 2022 - Fruits for All",
    "Longitude": 10131559.2386,
    "Latitude": 3164425.4987
  },
  {
    "Project_Title": "New Zealand 2022 - Waingake Native Restoration",
    "Longitude": 19789108.2388,
    "Latitude": -4698506.1505
  },
  {
    "Project_Title": "Indonesia 2022 - Sumatra Gunung Leuser National Park Buffer Zone ",
    "Longitude": 10938976.742,
    "Latitude": 386534.503
  },
  {
    "Project_Title": "Australia 2021/22 - Cassowary Coast Regeneration",
    "Longitude": 16243518.671,
    "Latitude": -1999005.932
  },
  {
    "Project_Title": "Indonesia 2022 - AZ Forest (Citarum River Grant)",
    "Longitude": 11943232.2812,
    "Latitude": -702616.5791
  },
  {
    "Project_Title": "Peru 2022 - Amazon reforestation through agroforestry",
    "Longitude": -8246269.213,
    "Latitude": -699004.7618
  },
  {
    "Project_Title": "Spain 2022 - Undabaso Forest",
    "Longitude": -297567.2703,
    "Latitude": 5347736.3048
  },
  {
    "Project_Title": "Australia 2022 - Ecological Restoration in Southwest Western Australia",
    "Longitude": 13090340.4494,
    "Latitude": -4053487.9985
  },
  {
    "Project_Title": "Portugal 2022 – Free Trees for Portugal",
    "Longitude": -947794.5161,
    "Latitude": 4540673.5482
  },
  {
    "Project_Title": "Oregon 2022 - North Santiam Replanting, Phase 1 (ORCA)",
    "Longitude": -13645794.3627,
    "Latitude": 5588486.4536
  },
  {
    "Project_Title": "California 2021 - Creek Fire Restoration",
    "Longitude": -13281869.8634,
    "Latitude": 4458221.4596
  },
  {
    "Project_Title": "Mexico 2022 - Monarch Area Reforestation",
    "Longitude": -11171077.8247,
    "Latitude": 2223996.0816
  },
  {
    "Project_Title": "Scotland 2022 - Boosting Native Woodland Connectivity at Loch Ardinning",
    "Longitude": -478033.5575,
    "Latitude": 7551734.0463
  },
  {
    "Project_Title": "California 2022 - Family Lands in Northern California",
    "Longitude": -13690628.3767,
    "Latitude": 4974168.0705
  },
  {
    "Project_Title": "Florida 2022 - Myakka State Forest Reforestation",
    "Longitude": -9157086.7706,
    "Latitude": 3121621.0674
  },
  {
    "Project_Title": "Hawaii 2022- Mauna Kea Restoration",
    "Longitude": -17307923.9604,
    "Latitude": 2260971.5989
  },
  {
    "Project_Title": "India 2022 - Sand Dunes & Biodiversity",
    "Longitude": 8615020.6245,
    "Latitude": 905998.1158
  },
  {
    "Project_Title": "Guatemala 2022 - Regenerative Agroforestry for Communities",
    "Longitude": -9887184.0177,
    "Latitude": 1782028.4866
  },
  {
    "Project_Title": " Ireland 2022 - Nationwide Community Planting",
    "Longitude": -840006.4135,
    "Latitude": 6999667.5006
  },
  {
    "Project_Title": "Georgia 2022 - North Georgia Restoration",
    "Longitude": -9342919.0468,
    "Latitude": 4032754.2153
  },
  {
    "Project_Title": "Zimbabwe 2022 - Nyaodza Community Reforestation ",
    "Longitude": 3282460.31,
    "Latitude": -1863702.5524
  },
  {
    "Project_Title": "Oregon 2022 - Whitewater Ranch Restoration ",
    "Longitude": -13649588.0197,
    "Latitude": 5484135.2522
  },
  {
    "Project_Title": "Philippines 2022 - NESTLE - Lanao Del Sur Bamboo Reforestation",
    "Longitude": 13868755.6588,
    "Latitude": 877687.1661
  },
  {
    "Project_Title": "California 2022 - Moonlight Fire Area Restoration Project",
    "Longitude": -13431226.8346,
    "Latitude": 4893960.6929
  },
  {
    "Project_Title": "Oregon 2022- Private Landowner Restoration",
    "Longitude": -13646424.9431,
    "Latitude": 5489296.5296
  },
  {
    "Project_Title": "Texas 2022 - Sutton TX Longleaf Restoration",
    "Longitude": -10470322.0142,
    "Latitude": 3694306.3539
  },
  {
    "Project_Title": "Romania 2022 - Wind damage reforestation in Transylvania",
    "Longitude": 2851432.9304,
    "Latitude": 5872626.6589
  },
  {
    "Project_Title": "Peru 2022 - Forest Recovery with Agroforestry Systems in Santa Isabel",
    "Longitude": -8344569.3094,
    "Latitude": -1094649.4918
  },
  {
    "Project_Title": "Alabama 2022 - TLA Longleaf Restoration ",
    "Longitude": -9666162.1788,
    "Latitude": 3657063.9938
  },
  {
    "Project_Title": "Florida 2022 - Little Big Econ State Forest ",
    "Longitude": -9029671.6636,
    "Latitude": 3334993.8253
  },
  {
    "Project_Title": "South Carolina 2022 -  Longleaf Restoration",
    "Longitude": -8923931.4356,
    "Latitude": 4118905.0143
  },
  {
    "Project_Title": "Malawi 2022 -  Reforestation & Landscape Restoration",
    "Longitude": 3722743.155,
    "Latitude": -1307281.3492
  },
  {
    "Project_Title": "Montana 2022 - Marshall Woods Reforestation",
    "Longitude": -12866969.8761,
    "Latitude": 6037626.1451
  },
  {
    "Project_Title": "Wisconsin 2022 - Chequamegon-Nicolet Reforestation ",
    "Longitude": -9849221.934,
    "Latitude": 5654239.1073
  },
  {
    "Project_Title": "Idaho 2022 - Shared Stewardship Reforestation",
    "Longitude": -12972972.3027,
    "Latitude": 6064837.7509
  },
  {
    "Project_Title": "Idaho 2022 - Shared Stewardship Reforestation #2",
    "Longitude": -12946833.3731,
    "Latitude": 6121259.9357
  },
  {
    "Project_Title": "Montana 2022 - Caribou Fire Restoration",
    "Longitude": -12828833.5997,
    "Latitude": 6271527.688
  },
  {
    "Project_Title": "Montana 2022 - Ashland Postfire Restoration",
    "Longitude": -12192472.2796,
    "Latitude": 5648055.5892
  },
  {
    "Project_Title": "Wyoming 2022 - Burroughs Creek Wildfire Regeneration",
    "Longitude": -12207466.8926,
    "Latitude": 5418220.9543
  },
  {
    "Project_Title": "Wyoming 2022 - Budworm/sugarloaf Reforestation",
    "Longitude": -12190467.0816,
    "Latitude": 5597955.3158
  },
  {
    "Project_Title": "California 2022 - Tennant Fire Recovery",
    "Longitude": -13604672.453,
    "Latitude": 5120503.3725
  },
  {
    "Project_Title": "Virginia 2022 - George Washington North Zone",
    "Longitude": -8756476.5635,
    "Latitude": 4729171.3645
  },
  {
    "Project_Title": "California 2022 - Minerva Fire Reforestation",
    "Longitude": -13465027.8291,
    "Latitude": 4852575.4073
  },
  {
    "Project_Title": "Arizona 2022 - Wallow Reforestation",
    "Longitude": -12178672.6703,
    "Latitude": 4004716.3717
  },
  {
    "Project_Title": "California 2022 - Trough Fire Reforestation",
    "Longitude": -13705532.0305,
    "Latitude": 4892862.5066
  },
  {
    "Project_Title": "Oregon 2022 - Ochoco Divide Highway Fire Restoration",
    "Longitude": -13399366.5396,
    "Latitude": 5546766.8858
  },
  {
    "Project_Title": "Australia 2022 - Revegetating Marna Banggara",
    "Longitude": 15302528.8482,
    "Latitude": -4089207.1271
  },
  {
    "Project_Title": "Thailand 2022 - Baan Ba Community Reforestation Program",
    "Longitude": 11530761.5523,
    "Latitude": 1716836.0298
  },
  {
    "Project_Title": "India 2022 - Sundarban Mangrove Restoration",
    "Longitude": -8196357.5208,
    "Latitude": 2227859.298
  },
  {
    "Project_Title": "India 2022 - Fruit Trees To Fight Hunger",
    "Longitude": 9221815.8451,
    "Latitude": 2759043.2972
  },
  {
    "Project_Title": "Brazil 2022 - Mantiqueira Mountains (Phase 1)",
    "Longitude": -5061488.9854,
    "Latitude": -2568752.6242
  },
  {
    "Project_Title": "Montana 2022 - Resilience Planting",
    "Longitude": -12774832.96,
    "Latitude": 6157306.6598
  },
  {
    "Project_Title": "Oregon 2022 - Port Orford Restoration (ORCA)",
    "Longitude": -13843025.7837,
    "Latitude": 5264364.99
  },
  {
    "Project_Title": "Oregon & Washington 2022 - State Wide Wildfire Restoration",
    "Longitude": -13637677.2572,
    "Latitude": 5364933.1928
  },
  {
    "Project_Title": "Idaho 2022 - Nez Perce-Clearwater National Forest",
    "Longitude": -12911549.5584,
    "Latitude": 5746044.3463
  },
  {
    "Project_Title": "England 2022 - Avon Reforestation",
    "Longitude": -230732.1011,
    "Latitude": 6702040.8122
  },
  {
    "Project_Title": "Portugal 2022 – Renature Leiria",
    "Longitude": -998625.724,
    "Latitude": 4836060.0728
  },
  {
    "Project_Title": "Appalachia 2022 - Multiple \"Legacy\" Minesview",
    "Longitude": -8795068.8591,
    "Latitude": 5053789.8663
  },
  {
    "Project_Title": "Panama 2022 - Transforming Livelihoods and Landscapes",
    "Longitude": -8928473.4411,
    "Latitude": 830639.8824
  },
  {
    "Project_Title": "Peru 2022 - San Martin",
    "Longitude": -8570736.9596,
    "Latitude": -775344.6443
  },
  {
    "Project_Title": "Costa Rica 2022 - Ridge to Reef",
    "Longitude": -9246853.579,
    "Latitude": 1019824.7325
  },
  {
    "Project_Title": "Pacific NW 2022 - Orca Whale Project ",
    "Longitude": -13590991.065,
    "Latitude": 5702973.3162
  },
  {
    "Project_Title": "Argentina 2022 - Bosques de Agua - Pampa de Achala - Sierras Grande de Cordoba",
    "Longitude": -7213060.5585,
    "Latitude": -3697843.6884
  },
  {
    "Project_Title": "Australia 2022 - Koala Wildlife Corridor in Northern NSW",
    "Longitude": 17043071.3366,
    "Latitude": -3337541.9303
  },
  {
    "Project_Title": "Wales 2022 - Farm Jubilee Woods",
    "Longitude": -514319.7841,
    "Latitude": 6812033.9463
  },
  {
    "Project_Title": "Australia 2022 - Project Platypus: Upper Wimmera Catchment",
    "Longitude": 15883443.3213,
    "Latitude": -4461558.8383
  },
  {
    "Project_Title": "California 2022 - August Complex Fire Reforestation ",
    "Longitude": -13664265.0715,
    "Latitude": 4856581.3521
  },
  {
    "Project_Title": "Vietnam 2022 – Dakrong Nature Reserve",
    "Longitude": 11915912.8306,
    "Latitude": 1477617.6182
  },
  {
    "Project_Title": "Nova Scotia 2022 - Victoria Park",
    "Longitude": -7041385.5545,
    "Latitude": 5675350.7131
  },
  {
    "Project_Title": "Maine 2022 - Bethel Community Forest-Plant it Forward Phase 2",
    "Longitude": -7885927.5059,
    "Latitude": 5534272.5445
  },
  {
    "Project_Title": "Brazil 2022 - Ecosystem Restoration in the Atlantic Rainforest of Rio de Janeiro",
    "Longitude": -4815597.2557,
    "Latitude": -2584450.9911
  },
  {
    "Project_Title": "Maryland 2022- Clean water for Chesapeake",
    "Longitude": -8749482.9521,
    "Latitude": 4798826.8853
  },
  {
    "Project_Title": "Rwanda 2022 - Kula Coffee and Shade Tree Project ",
    "Longitude": 3316883.5716,
    "Latitude": -200855.7799
  },
  {
    "Project_Title": "Ghana 2022 - Bamboo Restoration in Bandai Hills ",
    "Longitude": -113939.6466,
    "Latitude": 766001.642
  },
  {
    "Project_Title": "France 2022 - Water Resource Restoration",
    "Longitude": 622945.2341,
    "Latitude": 5447635.239
  },
  {
    "Project_Title": "Ontario 2022 – Growing Green Acres in Rural Ottawa ",
    "Longitude": -8411484.7355,
    "Latitude": 5638219.9583
  },
  {
    "Project_Title": "California 2022 - Susanville",
    "Longitude": -13435986.9228,
    "Latitude": 4911048.8234
  },
  {
    "Project_Title": "California 2022 – Sweathouse Reforestation",
    "Longitude": -13789654.422,
    "Latitude": 4994574.7534
  },
  {
    "Project_Title": "Mexico 2022 - Santa Anita Forest Fire Recovery",
    "Longitude": -13002144.9668,
    "Latitude": 3809898.8929
  },
  {
    "Project_Title": "British Columbia 2022 - Williams Lake Restoration",
    "Longitude": -13699843.5155,
    "Latitude": 6768772.3449
  },
  {
    "Project_Title": "British Columbia 2022 - Plateau Fire Restoration, Kluskus",
    "Longitude": -13849809.5935,
    "Latitude": 7001030.244
  },
  {
    "Project_Title": "Indonesia 2022 - Coastal Restoration in North Sumatra",
    "Longitude": 10753413.7911,
    "Latitude": 548212.726
  },
  {
    "Project_Title": "Malaysia 2022 – Regrow Borneo",
    "Longitude": 13127557.3827,
    "Latitude": 605422.5835
  },
  {
    "Project_Title": "Philippines 2022 - Rogongan Reforestation Project",
    "Longitude": 13849616.9551,
    "Latitude": 918927.6313
  },
  {
    "Project_Title": "Brazil 2022 - Planting Forests, Harvesting Water ",
    "Longitude": -4914280.5272,
    "Latitude": -2186956.2713
  },
  {
    "Project_Title": "Ontario 2022 - 50 Million Tree Program",
    "Longitude": -9552724.8625,
    "Latitude": 6558564.8269
  },
  {
    "Project_Title": "Nova Scotia 2022 - Melrose Hill Restoration Forest",
    "Longitude": -6824666.0191,
    "Latitude": 5794391.6089
  },
  {
    "Project_Title": "New Brunswick 2022 - Chignecto Isthmus Restoration Forest",
    "Longitude": -7146084.8429,
    "Latitude": 5781904.8702
  },
  {
    "Project_Title": "Nova Scotia 2022 - New Boston and Melrose Hill Rehabilitation",
    "Longitude": -6727607.7451,
    "Latitude": 5782191.3764
  },
  {
    "Project_Title": "California 2022 – McKinleyville Reforestation",
    "Longitude": -13809514.6763,
    "Latitude": 5003109.6111
  },
  {
    "Project_Title": "California 2022 – Butte Reforestation 1",
    "Longitude": -13521401.1325,
    "Latitude": 4880075.733
  },
  {
    "Project_Title": "California 2022 – Butte Reforestation 2",
    "Longitude": -13521401.1325,
    "Latitude": 4880075.733
  },
  {
    "Project_Title": "California 2022 – Tehama Reforestation 1",
    "Longitude": -13727072.2518,
    "Latitude": 4914396.7813
  },
  {
    "Project_Title": "California 2022 – Trinity Reforestation",
    "Longitude": -13727072.2518,
    "Latitude": 4914396.7813
  },
  {
    "Project_Title": "Haiti 2022 - Restoring Watersheds & Reversing Poverty",
    "Longitude": -8031492.3486,
    "Latitude": 2148799.5562
  },
  {
    "Project_Title": "Idaho 2022 – Idaho-Kootenai Reforestation",
    "Longitude": -12949190.1848,
    "Latitude": 5913055.7497
  },
  {
    "Project_Title": "India 2022 - Trees for Habitat Restoration and Farmer Livelihoods",
    "Longitude": 8710168.9255,
    "Latitude": 1166544.1185
  },
  {
    "Project_Title": "India 2022 - Women-led mangrove restoration Sundarbans",
    "Longitude": 9869909.34,
    "Latitude": 2542106.6182
  },
  {
    "Project_Title": "California 2022- Colusa County Reforestation ",
    "Longitude": -13653024.9422,
    "Latitude": 4755570.7435
  },
  {
    "Project_Title": "Oregon 2022 – Tualatin River Restoration (ORCA) ",
    "Longitude": -13673665.9469,
    "Latitude": 5682130.4283
  },
  {
    "Project_Title": "Guatemala 2022 - Spring and Mountain Reforestation, Tzununa ",
    "Longitude": -10157809.1193,
    "Latitude": 1659645.6662
  },
  {
    "Project_Title": "New Brunswick 2022 – Nashwaak Floodplain Forest Restoration",
    "Longitude": -7414320.6597,
    "Latitude": 5777020.2507
  },
  {
    "Project_Title": "Ontario 2022 - Grey Sauble Conservation",
    "Longitude": -8977582.364,
    "Latitude": 5543536.3065
  },
  {
    "Project_Title": "Nova Scotia 2022 - Restoration of Acadian Forest on Cape Breton",
    "Longitude": -6806785.1222,
    "Latitude": 5830684.0377
  },
  {
    "Project_Title": "Guatemala 2022 – Restoring the Southwest Coast of Guatemala ",
    "Longitude": -10232918.723,
    "Latitude": 1629452.8552
  },
  {
    "Project_Title": "Australia 2022 - Mornington Peninsula Koalas",
    "Longitude": 16156100.3988,
    "Latitude": -4633439.7138
  },
  {
    "Project_Title": "New Zealand 2022 - Papakura Stream Restoration",
    "Longitude": 19478377.1904,
    "Latitude": -4439645.8137
  },
  {
    "Project_Title": "Thailand 2022 - Hilltribes Forestry & Agroforestry",
    "Longitude": 11064863.1285,
    "Latitude": 2262265.8764
  },
  {
    "Project_Title": "Indonesia 2022 - Community Agroforestry as Wildlife Buffer",
    "Longitude": 10943237.2818,
    "Latitude": 376074.3485
  },
  {
    "Project_Title": "Ontario 2022 -  Highway of Heroes Afforestation",
    "Longitude": -8787495.0605,
    "Latitude": 5466769.5108
  },
  {
    "Project_Title": "Nova Scotia 2022 - Restoration for Climate and Community",
    "Longitude": -7168614.6522,
    "Latitude": 5567060.2232
  },
  {
    "Project_Title": "California 2022 - Tahoe Fires Restoration",
    "Longitude": -13354285.3184,
    "Latitude": 4701560.3702
  },
  {
    "Project_Title": "Oregon 2022- Holiday Farm Fire (ORCA)",
    "Longitude": -13643529.7235,
    "Latitude": 5485687.5
  },
  {
    "Project_Title": "Oregon 2022 - Riverside Fire (ORCA)",
    "Longitude": -13614961.079,
    "Latitude": 5613418.1993
  },
  {
    "Project_Title": "Mexico 2022 - Monarch Butterfly",
    "Longitude": -11167580.5893,
    "Latitude": 2201136.4977
  },
  {
    "Project_Title": "New Brunswick 2022 - Acadian Village Provincial Park",
    "Longitude": -7246247.8342,
    "Latitude": 6070223.2988
  },
  {
    "Project_Title": "Brazil 2022 - Sustainable Development in the Barra Velha Indigenous Territory",
    "Longitude": -4381615.1073,
    "Latitude": -1903063.354
  },
  {
    "Project_Title": "California 2022- Sonoma County Reforestation ",
    "Longitude": -13663340.9416,
    "Latitude": 4673735.224
  },
  {
    "Project_Title": "Dominican Republic 2022 - Restoring Watersheds & Agroforestry",
    "Longitude": -7868497.6477,
    "Latitude": 2127233.7198
  },
  {
    "Project_Title": "Nicaragua 2022 - San Antonio Estate Reforestation ",
    "Longitude": -9674268.8048,
    "Latitude": 1423104.4937
  },
  {
    "Project_Title": "Mexico 2022 – Jalisco, Querétaro and Puebla  ",
    "Longitude": -11485690.3388,
    "Latitude": 2322174.3009
  },
  {
    "Project_Title": "Nova Scotia 2022 - Hardwood Hill Restoration Project ",
    "Longitude": -6914106.3163,
    "Latitude": 5663140.5063
  },
  {
    "Project_Title": "Illinois 2022- Million Trees Project",
    "Longitude": -9892318.3843,
    "Latitude": 4819293.8455
  },
  {
    "Project_Title": "Ontario 2022 - The Miller Project Part 1",
    "Longitude": -8786752.1042,
    "Latitude": 5455270.7856
  },
  {
    "Project_Title": "British Columbia 2022 - 2BT Nazko Wildfire Reforestation",
    "Longitude": -13757921.1091,
    "Latitude": 6931309.8026
  },
  {
    "Project_Title": "Indonesia 2022 - Kalimantan Forest Fire Rehabilitation",
    "Longitude": 12685216.6176,
    "Latitude": -179347.8949
  },
  {
    "Project_Title": "Spain 2022 - Regenerative Agriculture",
    "Longitude": -393192.0354,
    "Latitude": 4853288.2524
  },
  {
    "Project_Title": "Arkansas 2022 - Green Bay Replanting Project",
    "Longitude": -10308564.8833,
    "Latitude": 4152971.3174
  },
  {
    "Project_Title": "Czech Republic 2022 -  Bark Beetle Recovery",
    "Longitude": 1474373.4627,
    "Latitude": 6498697.6094
  },
  {
    "Project_Title": "Portugal 2022 - Permaculture and regenerative farming",
    "Longitude": -932348.4158,
    "Latitude": 4653292.8518
  },
  {
    "Project_Title": "Tennessee 2022 - East TN Nursery Seedlings (Year 2)",
    "Longitude": -9414134.3797,
    "Latitude": 4197485.6484
  },
  {
    "Project_Title": "France 2022 - Water Resource Restoration (St-Germain)",
    "Longitude": -100522.511,
    "Latitude": 5655996.6872
  },
  {
    "Project_Title": "Czech Republic 2022 - CAT - Trees for local communities ",
    "Longitude": 1549286.7867,
    "Latitude": 6471316.8657
  },
  {
    "Project_Title": "Mexico 2022 - Watershed management in the state of Veracruz",
    "Longitude": -10823124.0756,
    "Latitude": 2174552.5289
  },
  {
    "Project_Title": "Alberta 2022 - Peace Region Riparian Restoration",
    "Longitude": -13253384.4636,
    "Latitude": 7427550.9343
  },
  {
    "Project_Title": "Ontario 2022 - Regreening Greater Sudbury ",
    "Longitude": -8997191.8856,
    "Latitude": 5852063.4287
  },
  {
    "Project_Title": "Maine 2022 - Reforestation of Maine Forests Part 1",
    "Longitude": -7788924.3729,
    "Latitude": 5868551.4904
  },
  {
    "Project_Title": "Québec 2022 - Reforestation of Abandoned Agricultural Lands",
    "Longitude": -8790997.7161,
    "Latitude": 6142396.4929
  },
  {
    "Project_Title": "Indonesia 2022 - Kalimantan Water Catchment Restoration",
    "Longitude": 13046116.9004,
    "Latitude": 206156.1626
  },
  {
    "Project_Title": "Australia 2022 - Threatened Species Habitat Restoration in WA",
    "Longitude": 13070300.0801,
    "Latitude": -3891316.4612
  },
  {
    "Project_Title": "Minnesota 2022 - Northern Minnesota Restoration",
    "Longitude": -10278853.2915,
    "Latitude": 6054794.5815
  },
  {
    "Project_Title": "México 2022 - Selva Maya",
    "Longitude": -9874204.735,
    "Latitude": 2078534.0232
  },
  {
    "Project_Title": "México 2022 - Mejores Alianzas Mejores Bosques",
    "Longitude": -11031262.4845,
    "Latitude": 2178589.5422
  },
  {
    "Project_Title": "México 2022 - Conservación del corredor Nevado Manantlán",
    "Longitude": -11533396.2843,
    "Latitude": 2230453.6707
  },
  {
    "Project_Title": "Panama 2022 - Ecological Corridor Reforestation",
    "Longitude": -8941575.2131,
    "Latitude": 835103.1076
  },
  {
    "Project_Title": "Costa Rica 2022 - Reforesting the Tropical Dry Forest of Costa Rica",
    "Longitude": -9526758.7085,
    "Latitude": 1204015.8195
  },
  {
    "Project_Title": "Honduras 2022 - Cordillera Nombre de Dios Agroforestry",
    "Longitude": -9796896.5369,
    "Latitude": 1677647.1992
  },
  {
    "Project_Title": "Quebec 2022 - A New Lung for East Montreal - Phase 2",
    "Longitude": -8178580.043,
    "Latitude": 5727681.4465
  },
  {
    "Project_Title": "Indonesia 2022 – Sabangau Peatland Restoration",
    "Longitude": 12651448.7629,
    "Latitude": -282266.8236
  },
  {
    "Project_Title": "New Zealand 2022 - Plant For A Change",
    "Longitude": 19463727.6456,
    "Latitude": -4432587.129
  },
  {
    "Project_Title": "Australia 2022 - TreeProject Victoria",
    "Longitude": 16202036.587,
    "Latitude": -4559833.8621
  },
  {
    "Project_Title": "British Columbia 2022 - Little Trees-Big Trees, GAT' AZI - Gat' CHO",
    "Longitude": -13728302.822,
    "Latitude": 7300806.1859
  },
  {
    "Project_Title": "Indonesia 2022 - Kalimantan community-led agroforestry",
    "Longitude": 12249167.775,
    "Latitude": 101012.7832
  },
  {
    "Project_Title": "Mexico 2022 - Huizilac ",
    "Longitude": -11050410.2507,
    "Latitude": 2168976.9363
  },
  {
    "Project_Title": "Indonesia 2022 - Sumatra Peatland Agroforestry",
    "Longitude": 11571679.3244,
    "Latitude": -140260.5827
  },
  {
    "Project_Title": "India 2022 – Plant for Punjab",
    "Longitude": 8455169.4714,
    "Latitude": 3513193.0216
  },
  {
    "Project_Title": "Mexico 2022 - Monarch High Forest Reforestation",
    "Longitude": -11156702.9607,
    "Latitude": 2238969.5422
  },
  {
    "Project_Title": "Mexico 2022 -  Queretaro semidesert reforestation ",
    "Longitude": -11158311.4717,
    "Latitude": 2242350.2689
  },
  {
    "Project_Title": "Australia 2022 - Regent Parrot Corridor Restoration",
    "Longitude": 15683969.1354,
    "Latitude": -4036559.8485
  },
  {
    "Project_Title": "Chile 2022 - Trees & Seas",
    "Longitude": -8214636.3314,
    "Latitude": -5147940.7868
  },
  {
    "Project_Title": "India 2022 - Agroforestry to Protect Tiger Habitat",
    "Longitude": 8519594.5514,
    "Latitude": 1334750.8008
  },
  {
    "Project_Title": "Philippines 2022 – Community Forestry Palawan",
    "Longitude": 13173673.8194,
    "Latitude": 1068953.878
  },
  {
    "Project_Title": "California 2022 - Bald Fire reforestation",
    "Longitude": -13517257.7097,
    "Latitude": 5011729.5591
  },
  {
    "Project_Title": "India 2022 – Kaveri River Basin",
    "Longitude": 8584875.1383,
    "Latitude": 1342588.1482
  },
  {
    "Project_Title": "Vietnam 2022 - Riparian Restoration & Sustainable Livelihoods",
    "Longitude": 11988713.6959,
    "Latitude": 1195518.3987
  },
  {
    "Project_Title": "Armenia 2022 - North Bazum",
    "Longitude": 4928170.1127,
    "Latitude": 5004527.6567
  },
  {
    "Project_Title": "Philippines 2022 - Mt Pinatubo Youth-led Restoration",
    "Longitude": 13374071.4451,
    "Latitude": 1698289.1009
  },
  {
    "Project_Title": "México 2022 - Nevado de Toluca Reforestation",
    "Longitude": -11101734.4626,
    "Latitude": 2171864.121
  },
  {
    "Project_Title": "New Brunswick 2022 - Luciphy East Bird Sanctuary",
    "Longitude": -7148806.5276,
    "Latitude": 5777254.1496
  },
  {
    "Project_Title": "New Brunswick 2022 - Upper Aboushagan Bird Sancturary",
    "Longitude": -7165253.5594,
    "Latitude": 5781124.3243
  },
  {
    "Project_Title": "Nova Scotia 2022 - Lapland Restoration",
    "Longitude": -7203194.5269,
    "Latitude": 5508813.3937
  },
  {
    "Project_Title": "New Zealand 2022 - Freshwater Improvement of the Turanganui Estuary",
    "Longitude": 19815077.9405,
    "Latitude": -4671799.8208
  },
  {
    "Project_Title": "Bangladesh 2022 - Sundarbans Mangrove Restoration",
    "Longitude": 9971316.8387,
    "Latitude": 2574453.4592
  },
  {
    "Project_Title": "Mexico 2022 - Reforestación Naucalpan",
    "Longitude": -11065429.6723,
    "Latitude": 2211938.3137
  },
  {
    "Project_Title": "Brazil 2022 - Foresting 4us",
    "Longitude": -7132510.0433,
    "Latitude": -994667.6903
  },
  {
    "Project_Title": "Switzerland 2022 - Allaman Agroforestry ",
    "Longitude": 710911.6836,
    "Latitude": 5855707.6954
  },
  {
    "Project_Title": "Ontario 2022 - Otonabee Region Tree Planting ",
    "Longitude": -8735485.0115,
    "Latitude": 5528892.0032
  },
  {
    "Project_Title": "Brazil 2022 -  Bacia do Rio Claro",
    "Longitude": -5718487.0911,
    "Latitude": -1920988.334
  },
  {
    "Project_Title": "Egypt 2022 - Greening the Desert ",
    "Longitude": 3239148.216,
    "Latitude": 3279723.8605
  },
  {
    "Project_Title": "Switzerland 2022 - Educational Reforestation",
    "Longitude": 711415.8774,
    "Latitude": 5856073.4708
  },
  {
    "Project_Title": "Germany 2022 - Carlsberg Reforestation",
    "Longitude": 896407.0992,
    "Latitude": 6357611.1518
  },
  {
    "Project_Title": "Hungary 2022 - Nyim & Dombfalva",
    "Longitude": 2014519.7872,
    "Latitude": 5911257.6107
  },
  {
    "Project_Title": "Spain 2022 – Reforestación Málaga",
    "Longitude": -500953.7263,
    "Latitude": 4401060.2346
  },
  {
    "Project_Title": "Poland 2022 - Ogrodzieniec Autumn Reforestation ",
    "Longitude": 2169623.6404,
    "Latitude": 6522754.8037
  },
  {
    "Project_Title": "Philippines 2022 - Indigenous-led Agroforestry",
    "Longitude": 13851297.7459,
    "Latitude": 920955.374
  },
  {
    "Project_Title": "Italy 2022 - Turin - Agroforestry",
    "Longitude": 849980.7512,
    "Latitude": 5622670.1652
  },
  {
    "Project_Title": "Netherlands 2022 - CAT - Den Bosch",
    "Longitude": 601466.2219,
    "Latitude": 6749479.7062
  },
  {
    "Project_Title": "Uganda 2023 - Albertine Rift",
    "Longitude": 3479759.2864,
    "Latitude": 165088.9083
  },
  {
    "Project_Title": "Denmark 2023 - Jutland",
    "Longitude": 1129731.8636,
    "Latitude": 7595957.9385
  },
  {
    "Project_Title": "Romania 2023 - The story of the oak forests of Ciuc",
    "Longitude": 2859960.4676,
    "Latitude": 5868551.5115
  },
  {
    "Project_Title": "Brazil 2022 - Make the Forest Flourish II",
    "Longitude": -7882755.2255,
    "Latitude": -1008703.242
  },
  {
    "Project_Title": "Indonesia 2023 - Bali Community Forest",
    "Longitude": 12838717.9912,
    "Latitude": -909317.6138
  },
  {
    "Project_Title": "New Zealand 2023 - Waingake Native Restoration",
    "Longitude": 19789436.3975,
    "Latitude": -4699589.768
  },
  {
    "Project_Title": "California 2023 - Amargosa River Watershed Restoration ",
    "Longitude": -12965293.6624,
    "Latitude": 4359138.9305
  },
  {
    "Project_Title": "California 2023 - Creek Fire Restoration",
    "Longitude": -13282574.8498,
    "Latitude": 4453947.9702
  },
  {
    "Project_Title": "Oregon 2023 - State Wide Wildfire Restoration",
    "Longitude": -13683970.6474,
    "Latitude": 5367244.7672
  },
  {
    "Project_Title": "England 2023 - Essex Forest Initiative",
    "Longitude": 63427.3645,
    "Latitude": 6765942.2745
  },
  {
    "Project_Title": "California 2023 - Red-Salmon Fire Restoration (Phase 1)",
    "Longitude": -13755335.1907,
    "Latitude": 5018304.5115
  },
  {
    "Project_Title": "California 2023 - Northern California Wildfire Restoration",
    "Longitude": -13643381.1788,
    "Latitude": 4674584.5652
  },
  {
    "Project_Title": "Georgia 2023 - North Georgia Restoration ",
    "Longitude": -9342919.0468,
    "Latitude": 4032754.2153
  },
  {
    "Project_Title": "Philippines 2023 - Indigenous Bamboo & Native Tree Reforestation",
    "Longitude": 13911898.4403,
    "Latitude": 898856.0944
  },
  {
    "Project_Title": "Malawi 2023 -  Reforestation & Landscape Restoration",
    "Longitude": 3722400.1452,
    "Latitude": -1325317.8275
  },
  {
    "Project_Title": "Colorado 2023 - White River Cone Collection",
    "Longitude": -11923129.7623,
    "Latitude": 4789620.2872
  },
  {
    "Project_Title": "Brazil 2023 - Corridors for Life (Phase I)",
    "Longitude": -5806828.626,
    "Latitude": -2565916.4433
  },
  {
    "Project_Title": "California 2023 - Howe Creek Restoration ",
    "Longitude": -13822534.4036,
    "Latitude": 4935264.66
  },
  {
    "Project_Title": "Brazil 2023 - Forests4Water",
    "Longitude": -4735850.0453,
    "Latitude": -2380530.2252
  },
  {
    "Project_Title": "Argentina 2023 - Cholila, Restauración de bosques nativos degradados",
    "Longitude": -7986046.772,
    "Latitude": -5227893.8168
  },
  {
    "Project_Title": "California 2023 - Hog and Sheep Fire Restoration",
    "Longitude": -13437598.7066,
    "Latitude": 4944638.8264
  },
  {
    "Project_Title": "British Columbia 2023 - Canim and Plateau Fires (Drone Planting)",
    "Longitude": -13533635.69,
    "Latitude": 6710175.0054
  },
  {
    "Project_Title": "California 2023 - Emergency Forest Restoration Team (EFRT)",
    "Longitude": -13449449.8909,
    "Latitude": 4876159.7181
  },
  {
    "Project_Title": "California 2023 - Longbell Ranch",
    "Longitude": -13568315.3849,
    "Latitude": 5106426.504
  },
  {
    "Project_Title": "Brazil 2023 - Intelligent Forests",
    "Longitude": -5508196.4155,
    "Latitude": -2492101.8615
  },
  {
    "Project_Title": "Andes 2023 - High Andes Polylepis Forest",
    "Longitude": -7877580.8217,
    "Latitude": -1895540.0339
  },
  {
    "Project_Title": "Philippines 2023 - Indigenous Reforestation in Eagle Habitat",
    "Longitude": 13520853.6187,
    "Latitude": 1759445.1743
  },
  {
    "Project_Title": "Alberta 2023 - Mistehae Lake (Pilot)",
    "Longitude": -12720669.8828,
    "Latitude": 7546172.936
  },
  {
    "Project_Title": "Oregon 2023 - Scio Reforestation",
    "Longitude": -13664592.4176,
    "Latitude": 5570563.8932
  },
  {
    "Project_Title": "Oregon 2023 - Lyons County Restoration ",
    "Longitude": -13645582.4327,
    "Latitude": 5589750.2949
  },
  {
    "Project_Title": "Nova Scotia 2023 - Cape Breton Highlands National Park",
    "Longitude": -6772973.0124,
    "Latitude": 5907348.4601
  },
  {
    "Project_Title": "England 2023 - Avon Reforestation",
    "Longitude": -230732.1011,
    "Latitude": 6702040.8122
  },
  {
    "Project_Title": "Ontario 2023 - Larose Forest",
    "Longitude": -8367257.8446,
    "Latitude": 5681416.7418
  },
  {
    "Project_Title": "Ohio 2023 - Wolf Creek Riparian Reforestation",
    "Longitude": -9268911.614,
    "Latitude": 5047171.0801
  },
  {
    "Project_Title": "Sri Lanka 2023 - Balangoda Restoration",
    "Longitude": 8995916.9212,
    "Latitude": 737783.7961
  },
  {
    "Project_Title": "Peru 2023 - Ucayali",
    "Longitude": -8269000.8489,
    "Latitude": -938054.4112
  },
  {
    "Project_Title": "Alberta 2023 - Sparrow Project",
    "Longitude": -12624728.1778,
    "Latitude": 7253562.8442
  },
  {
    "Project_Title": "Timor-Leste 2023 - Community Forestry",
    "Longitude": 14100468.8709,
    "Latitude": -964715.7356
  },
  {
    "Project_Title": "Honduras 2023 - Regenerative Agroforestry with Inga and Fruit Trees",
    "Longitude": -9668852.2989,
    "Latitude": 1759760.8317
  },
  {
    "Project_Title": "Oregon 2023 - Marion County Parks Reforestation",
    "Longitude": -13630318.3041,
    "Latitude": 5586534.9461
  },
  {
    "Project_Title": "Panama 2023 - Darien Restoration Initiative ",
    "Longitude": -8638814.7649,
    "Latitude": 893752.9514
  },
  {
    "Project_Title": "Costa Rica 2023 - Reforesting the Tropical Dry Forest of Costa Rica",
    "Longitude": -9526758.7085,
    "Latitude": 1204015.8195
  },
  {
    "Project_Title": "California 2023 - Mendocino and Sonoma Counties Restoration (Phase 2)",
    "Longitude": -13688769.831,
    "Latitude": 4665493.7213
  },
  {
    "Project_Title": "Delaware 2023 - Bullseye Ferry Planting ",
    "Longitude": -8376256.526,
    "Latitude": 4663844.6732
  },
  {
    "Project_Title": "Scotland 2023 - Free Trees for Scotland!",
    "Longitude": -329145.0799,
    "Latitude": 7385410.6038
  },
  {
    "Project_Title": "Mexico 2023 – Monarch Area Reforestation in Michoacán",
    "Longitude": -11281133.984,
    "Latitude": 2206968.28
  },
  {
    "Project_Title": "Brazil 2023 - Make the Forest Flourish III",
    "Longitude": -7882755.2255,
    "Latitude": -1008703.242
  },
  {
    "Project_Title": "Australia 2023 - Threatened Species Habitat Restoration in WA",
    "Longitude": 13020700.501,
    "Latitude": -3939489.2227
  },
  {
    "Project_Title": "Oregon 2023 - North Santiam Replanting, Phase 2 (ORCA)",
    "Longitude": -13645794.3627,
    "Latitude": 5588486.4536
  },
  {
    "Project_Title": "California 2023 - Alder Creek Planting",
    "Longitude": -13205144.3849,
    "Latitude": 4326382.5045
  },
  {
    "Project_Title": "California 2023 - Bunnell Ranch ",
    "Longitude": -13447497.8146,
    "Latitude": 4925375.3307
  },
  {
    "Project_Title": "California 2023 - Val Ranch ",
    "Longitude": -13654802.848,
    "Latitude": 4742995.1291
  },
  {
    "Project_Title": "Scotland 2023 - Woodland creation at Dullatur",
    "Longitude": -443881.2709,
    "Latitude": 7554181.1488
  },
  {
    "Project_Title": "India 2023 - Agroforestry to Protect Tiger Habitat",
    "Longitude": 8519594.5514,
    "Latitude": 1334750.8008
  },
  {
    "Project_Title": "Australia 2023 - Regent Parrot Corridor Restoration",
    "Longitude": 15683969.1354,
    "Latitude": -4036559.8485
  },
  {
    "Project_Title": "Alabama 2023 - Restoring Longleaf Pine ",
    "Longitude": -9653803.5735,
    "Latitude": 3732251.0854
  },
  {
    "Project_Title": "South East 2023 - Species Conservation and Longleaf Pine Restoration",
    "Longitude": -9176992.2495,
    "Latitude": 3791563.6871
  },
  {
    "Project_Title": "Indonesia 2023 - Kubu Raya Mangrove Restoration",
    "Longitude": 12158142.896,
    "Latitude": -60479.058
  },
  {
    "Project_Title": "Mexico 2023 - Reforestation in and around the Monarch Biosphere",
    "Longitude": -11163853.4235,
    "Latitude": 2208859.9683
  },
  {
    "Project_Title": "Honduras 2023 - Agroforestry and Biodiversity Conservation",
    "Longitude": -9777878.1351,
    "Latitude": 1661472.7211
  },
  {
    "Project_Title": "Texas 2023 - Restoration of Longleaf Pine",
    "Longitude": -10507139.9395,
    "Latitude": 3562598.019
  },
  {
    "Project_Title": "Mississippi 2023 - Longleaf Restoration",
    "Longitude": -9945335.071,
    "Latitude": 3617647.3034
  },
  {
    "Project_Title": "Belgium 2023 - Reforestation Program",
    "Longitude": 562119.5464,
    "Latitude": 6501145.1946
  },
  {
    "Project_Title": "Mexico 2023 - Monarch Corridor in the State of Mexico",
    "Longitude": -11109457.436,
    "Latitude": 2167596.0492
  },
  {
    "Project_Title": "Philippines 2023 - Mt Pinatubo Youth-led Restoration",
    "Longitude": 13374071.4451,
    "Latitude": 1698289.1009
  },
  {
    "Project_Title": "Talladega 2023 - Blue Ridge Mountains Restoration ",
    "Longitude": -9520547.5752,
    "Latitude": 4112649.7126
  },
  {
    "Project_Title": "Georgia 2023 - Longleaf Restoration of At-Risk Landscapes",
    "Longitude": -9229178.6042,
    "Latitude": 3783994.3367
  },
  {
    "Project_Title": "British Columbia 2023 - AR Planting Pilots",
    "Longitude": -13644266.8923,
    "Latitude": 6807832.7697
  },
  {
    "Project_Title": "California 2023 - Susanville Family Lands",
    "Longitude": -13438376.841,
    "Latitude": 4915649.2703
  },
  {
    "Project_Title": "England 2023 - Community Forest Restoration",
    "Longitude": -254668.9387,
    "Latitude": 7083939.9403
  },
  {
    "Project_Title": "Bangladesh 2023 - Sundarbans Mangrove Restoration",
    "Longitude": 9971316.8387,
    "Latitude": 2574453.4592
  },
  {
    "Project_Title": "Peru 2023 - Amazon Agroforestry and Silvopasture ",
    "Longitude": -8250251.0633,
    "Latitude": -702014.524
  },
  {
    "Project_Title": "México 2023 – Reforestation in Jalisco, Michoacán, and Puebla ",
    "Longitude": -10978488.2639,
    "Latitude": 2201933.3012
  },
  {
    "Project_Title": "Mexico 2023 – Mangrove Reforestation on the coast of Oaxaca",
    "Longitude": -10795782.724,
    "Latitude": 1781847.5184
  },
  {
    "Project_Title": "Ohio 2023 - Farmington Forested Wetlands Restoration",
    "Longitude": -9017108.5566,
    "Latitude": 5071962.0382
  },
  {
    "Project_Title": "Florida 2023 - Longleaf Restoration",
    "Longitude": -9183750.4146,
    "Latitude": 3368567.5521
  },
  {
    "Project_Title": " Portugal 2023 - Free Trees for Portugal",
    "Longitude": -889443.7734,
    "Latitude": 4815148.1559
  },
  {
    "Project_Title": "Texas 2023 - Tornado Restoration, Bingham Longleaf Reforestation",
    "Longitude": -10545357.3678,
    "Latitude": 3667263.2615
  },
  {
    "Project_Title": "Montana 2023 - Ashland District Post Fire Restoration",
    "Longitude": -11848304.8081,
    "Latitude": 5824390.1916
  },
  {
    "Project_Title": "Washington 2023 - Woodard Restoration Phase 2",
    "Longitude": -13584875.2835,
    "Latitude": 5720636.4258
  },
  {
    "Project_Title": "Utah 2023 - Shingle Fire Restoration",
    "Longitude": -12515555.3944,
    "Latitude": 4480061.4023
  },
  {
    "Project_Title": "Arizona 2023 - Sheridan Fire Reforestation",
    "Longitude": -12563909.7203,
    "Latitude": 4136738.0251
  },
  {
    "Project_Title": "Arizona 2023 - Yarrow 2 Planting",
    "Longitude": -12294331.8401,
    "Latitude": 4077121.0209
  },
  {
    "Project_Title": "Wyoming 2023 - Budworm Response Reforestation",
    "Longitude": -12185402.1561,
    "Latitude": 5603450.9338
  },
  {
    "Project_Title": "Colorado 2023 - West Fork Wildfire Reforestation",
    "Longitude": -11889075.1597,
    "Latitude": 4528084.8182
  },
  {
    "Project_Title": "Colorado 2023 - Silver Creek Fire Reforestation",
    "Longitude": -11878699.2592,
    "Latitude": 4902950.3991
  },
  {
    "Project_Title": "Wyoming 2023 - Capitol Salvage",
    "Longitude": -11849424.6822,
    "Latitude": 5079082.5462
  },
  {
    "Project_Title": "Michigan 2023 - Kirtland's Warbler Jack Pine Planting ",
    "Longitude": -9436872.3875,
    "Latitude": 5838041.2422
  },
  {
    "Project_Title": "Idaho 2023 - Crown Royal Reforestation",
    "Longitude": -12924326.4645,
    "Latitude": 5705888.9462
  },
  {
    "Project_Title": "Idaho 2023 - Stewardship Reforestation Boundary and Bonner Counties",
    "Longitude": -12975158.3949,
    "Latitude": 6107535.7913
  },
  {
    "Project_Title": "California 2023 - Lake Fire Reforestation ",
    "Longitude": -13172435.3456,
    "Latitude": 4084393.5704
  },
  {
    "Project_Title": "Maryland 2023 - Clean Water for Chesapeake Bay ",
    "Longitude": -8722348.6659,
    "Latitude": 4799709.7396
  },
  {
    "Project_Title": "Philippines 2023 - Sorsogon Biodiversity & Watershed Restoration [Phase 1]",
    "Longitude": 13803262.7845,
    "Latitude": 1436705.3289
  },
  {
    "Project_Title": "Brazil 2023 - Ação Regeneração ",
    "Longitude": -5096796.0892,
    "Latitude": -2634548.4515
  },
  {
    "Project_Title": "Spain 2023 - Regenerative Agriculture",
    "Longitude": -443163.2613,
    "Latitude": 4875432.6987
  },
  {
    "Project_Title": "Michigan 2023 - DNR Northern Hardwood Restoration",
    "Longitude": -9532393.9728,
    "Latitude": 5852127.8563
  },
  {
    "Project_Title": "Mexico 2023 - Reforestation Bajío Zone",
    "Longitude": -11143275.4924,
    "Latitude": 2300062.7381
  },
  {
    "Project_Title": "Mexico 2023 - Monarch High Forest Reforestation ",
    "Longitude": -11178837.0715,
    "Latitude": 2234160.0379
  },
  {
    "Project_Title": "Peru 2023 - Pucallpa Restoration Project",
    "Longitude": -8315683.7027,
    "Latitude": -943801.9098
  },
  {
    "Project_Title": "Brazil 2023 - Amazon Muvuca",
    "Longitude": -6385904.2025,
    "Latitude": -1116440.3959
  },
  {
    "Project_Title": "Alberta 2023 - Mistehae Lake",
    "Longitude": -12717432.1332,
    "Latitude": 7539304.0581
  },
  {},
  {
    "Project_Title": "New Zealand 2023 - Nelson/Tasman Native Trees",
    "Longitude": 19239195.9321,
    "Latitude": -5030764.0388
  },
  {
    "Project_Title": "California 2023 - Feather River Watershed Fire Recovery ",
    "Longitude": -13476124.6903,
    "Latitude": 4883600.0351
  },
  {
    "Project_Title": "Czech Republic 2023 - CAT - Trees for Communities",
    "Longitude": 1739294.9086,
    "Latitude": 6389977.155
  },
  {
    "Project_Title": "Italy 2023 - Emilia Romagna (Phase 1)",
    "Longitude": 1329694.6196,
    "Latitude": 5502583.5833
  },
  {
    "Project_Title": "Minnesota 2023 - Restoring Resilient Forests",
    "Longitude": -10158588.2655,
    "Latitude": 6029162.3771
  },
  {
    "Project_Title": "India 2023 - Fruit Trees for Sustainable Livelihoods",
    "Longitude": 8140049.2024,
    "Latitude": 2224229.0164
  },
  {
    "Project_Title": "Belgium 2023 - Brussels Greener Communities",
    "Longitude": 486523.1225,
    "Latitude": 6592272.8397
  },
  {
    "Project_Title": "Florida 2023 - Eglin Air Force Base",
    "Longitude": -9676968.8,
    "Latitude": 3567410.3558
  },
  {
    "Project_Title": "Colorado 2023 - Gunnison Spruce Beetle Tree Planting",
    "Longitude": -11902669.5738,
    "Latitude": 4588824.2966
  },
  {
    "Project_Title": "Washington 2023 - Mason Riparian Restoration (ORCA)",
    "Longitude": -13716144.5183,
    "Latitude": 5984126.1079
  },
  {
    "Project_Title": "California 2023 - Carr Fire Wildfire Restoration",
    "Longitude": -13648516.2801,
    "Latitude": 4985931.2627
  },
  {
    "Project_Title": "California 2023 - Coffee Creek Restoration",
    "Longitude": -13666468.1065,
    "Latitude": 5027001.7281
  },
  {
    "Project_Title": "Ireland 2023 - Nationwide Community Tree Cover",
    "Longitude": -684859.4841,
    "Latitude": 7369606.0599
  },
  {
    "Project_Title": "Portugal 2023 - Renature Estrela",
    "Longitude": -841371.629,
    "Latitude": 4904758.7861
  },
  {
    "Project_Title": "Indonesia 2023 - Habitat Restoration for Rhino, Elephant, & Tiger",
    "Longitude": 11755379.8835,
    "Latitude": -556442.2088
  },
  {
    "Project_Title": "Indonesia 2023 - Kubung Agroforestry for Soil Restoration",
    "Longitude": 12349793.3923,
    "Latitude": -186453.4892
  },
  {
    "Project_Title": "California 2023 - Rim Wildfire Restoration",
    "Longitude": -13351405.5277,
    "Latitude": 4558411.7026
  },
  {
    "Project_Title": "New Brunswick 2023 - Poucette Road Reforestation",
    "Longitude": -7158278.8256,
    "Latitude": 5800412.7708
  },
  {
    "Project_Title": "New Brunswick 2023 - Adopt a Clearcut",
    "Longitude": -6814118.7857,
    "Latitude": 5744658.9386
  },
  {
    "Project_Title": "Nepal 2023 - Mount Everest Community Restoration",
    "Longitude": 9656594.7985,
    "Latitude": 3229515.8519
  },
  {
    "Project_Title": "Bhutan 2023 - Mountain Hazelnuts for Livelihood & Climate",
    "Longitude": 10198813.686,
    "Latitude": 3161576.8175
  },
  {
    "Project_Title": "Australia 2023 - Ecological Restoration in South-West WA",
    "Longitude": 13090340.4494,
    "Latitude": -4053487.9985
  },
  {
    "Project_Title": "Nicaragua 2023 - Macadamia Agroforestry ",
    "Longitude": -9567363.2097,
    "Latitude": 1499602.9209
  },
  {
    "Project_Title": "Myanmar 2023 - Community Mangrove Restoration",
    "Longitude": 10614439.6745,
    "Latitude": 1777128.6411
  },
  {
    "Project_Title": "British Columbia 2023- Nazko Wildfire Restoration Project",
    "Longitude": -13800809.5589,
    "Latitude": 6978238.228
  },
  {
    "Project_Title": "Oregon 2023 - Floodplain Forest Revegetation (ORCA)",
    "Longitude": -13708522.829,
    "Latitude": 5579958.0299
  },
  {
    "Project_Title": "Bhutan 2023 - Land Restoration for Nature & People",
    "Longitude": 9967189.2545,
    "Latitude": 3161620.1124
  },
  {
    "Project_Title": "Kenya 2023 - Upscale of drylands restoration in Kitui and Tharaka Nithi Counties",
    "Longitude": 4233872.3333,
    "Latitude": -177457.1343
  },
  {
    "Project_Title": "British Columbia 2023- Yunesit'in rehabilitation",
    "Longitude": -13763617.8506,
    "Latitude": 6732583.5626
  },
  {
    "Project_Title": "Nova Scotia 2023 - Cape Breton Highlands Restoration",
    "Longitude": -6754028.9665,
    "Latitude": 5913387.6542
  },
  {
    "Project_Title": "Washington 2023 - Spokane River Restoration Community Plantings",
    "Longitude": -13036026.7793,
    "Latitude": 6073779.2999
  },
  {
    "Project_Title": "New Brunswick 2023 - Fort Folly First Nation",
    "Longitude": -7179850.4946,
    "Latitude": 5762873.4172
  },
  {
    "Project_Title": "Ontario 2023 – Green Acres in Rural Ottawa",
    "Longitude": -8411484.7355,
    "Latitude": 5638219.9583
  },
  {
    "Project_Title": "Czech Republic 2023 -  Climate and Bark Beetle Restoration",
    "Longitude": 1477708.3541,
    "Latitude": 6499258.3558
  },
  {
    "Project_Title": "Germany 2023 -  Climate Resilient Restoration",
    "Longitude": 1308420.6256,
    "Latitude": 6777430.2169
  },
  {
    "Project_Title": "California 2023 - Santa Cruz Mountains Fire Restoration",
    "Longitude": -13600966.4936,
    "Latitude": 4465824.4687
  },
  {
    "Project_Title": "Australia 2023 - Watchbox Wetland Restoration",
    "Longitude": 16095723.0558,
    "Latitude": -4455139.6407
  },
  {
    "Project_Title": "California 2023 - Fire Restoration Brush Creek",
    "Longitude": -13506823.7227,
    "Latitude": 4820523.3541
  },
  {
    "Project_Title": "Southeast 2023 - US Agroforestry ",
    "Longitude": -9190579.3388,
    "Latitude": 4875910.8212
  },
  {
    "Project_Title": "Australia 2023 - Rejuvenation Trees - Kardutjaanup",
    "Longitude": 13514768.1049,
    "Latitude": -3889624.7993
  },
  {
    "Project_Title": "Appalachia 2023 - Mine Site Rehabilitation and Restoration",
    "Longitude": -8861957.18,
    "Latitude": 5076527.2402
  },
  {
    "Project_Title": "Oregon 2023 - Family Forest Restoration",
    "Longitude": -13749462.5666,
    "Latitude": 5359169.5395
  },
  {
    "Project_Title": "Oregon 2023 - Wapato Lake National Wildlife Refuge (ORCA)",
    "Longitude": -13706375.053,
    "Latitude": 5687466.0631
  },
  {
    "Project_Title": "Romania 2023 - Forest for climate resilience, Bălan bear sanctuary",
    "Longitude": 2863269.7778,
    "Latitude": 5895501.4591
  },
  {
    "Project_Title": "Lithuania 2023 - Vilnius Forest of Children",
    "Longitude": 2810049.9943,
    "Latitude": 7312040.5207
  },
  {
    "Project_Title": "Washington 2023 - Private Land Bolt Creek Fire Restoration",
    "Longitude": -13520423.8253,
    "Latitude": 6067179.9413
  },
  {
    "Project_Title": "Dominican Republic 2023 – Restoring Watersheds & Agroforestry",
    "Longitude": -7806650.2095,
    "Latitude": 2134943.7199
  },
  {
    "Project_Title": "China 2023 - Native Trees as Bioshield, & Land Restoration",
    "Longitude": 13336909.7819,
    "Latitude": 6002865.2137
  },
  {
    "Project_Title": "Thailand 2023 - Hilltribes Forestry & Agroforestry",
    "Longitude": 11084978.2454,
    "Latitude": 2269749.4185
  },
  {
    "Project_Title": "Netherlands 2023 - Community, Agroforestry and Cooperative Planting",
    "Longitude": 591375.6154,
    "Latitude": 6799201.051
  },
  {
    "Project_Title": "Thailand 2023 - Reforestation for Youth, Farmers, & Community",
    "Longitude": 11542694.3672,
    "Latitude": 1725282.7207
  },
  {
    "Project_Title": "Oregon / Washington 2023 - Lower Columbia Community Planting Projects ORCA",
    "Longitude": -13657169.1731,
    "Latitude": 5727966.045
  },
  {
    "Project_Title": "Iceland 2023 - Dragon's Nest Forest",
    "Longitude": -1531685.3941,
    "Latitude": 9644615.3818
  },
  {
    "Project_Title": "California 2023 - Caldor Forest and Community Reforestation Project",
    "Longitude": -13415538.6344,
    "Latitude": 4671385.9744
  },
  {
    "Project_Title": "Brazil 2024 - Araguaia Biodiversity Corridor",
    "Longitude": -5576825.4516,
    "Latitude": -1028119.393
  },
  {
    "Project_Title": "Brazil 2024 - Mantiqueira Mountains (Phase 2)",
    "Longitude": -5061488.9854,
    "Latitude": -2568752.6242
  },
  {
    "Project_Title": "Brazil 2023 - Courageous Land",
    "Longitude": -6757642.6532,
    "Latitude": -23816.2593
  }
]
